Workbook

Sheet README
B2: Status | C2: Definition
B3: In Design | C3: Test case is being written or updated. Requirements are being analyzed Steps and expected results are being documented Not ready for execution
B4: Ready | C4: Test case is fully designed and approved for execution. Steps complete Test data identified Awaiting execution
B5: Review Completed | C5: Test case has been peer-reviewed or approved by QA Lead / Business. Content validated Coverage confirmed No design gaps Ready for formal execution
B6: Pass | C6: Test case executed successfully. Actual result matches expected result No defect logged Functionality works as designed
B7: Fail | C7: Test case executed and did not meet expected result. Defect identified Defect logged in tracking system Requires fix and retest
B8: Blocked | C8: Test case cannot be executed due to external dependency. Examples: Environment issue Data unavailable Integration down Build not deployed Access issue
B9: No Run | C9: Test case has not yet been executed. Not started Waiting for environment Waiting for release window Still in backlog

Sheet Coaching log
A1: if Yellow | B1: Existing Defects
A2: =COUNT(A4:A61) -> 58
A3: Test Case ID | B3: Test Description/Title | C3: Module / Feature | D3: Preconditions | E3: Test Steps | F3: Test Data/ User | G3: Expected Result | H3: Actual outcome | I3: Status | J3: Existing Defect
A4: 1 | B4: Verify that admin has login to ECMS SF application | C4: Monitoring log /Coaching log | E4: Login SF-->ECMS Application | F4: Internal admin | G4: The vendor is able to login to ECMS SF homepage | H4: working as Excepted | I4: Pass
A5: 2 | B5: The admin is able to create a coaching log | C5: Monitoring log /Coaching log | D5: That admin should be Provisioned perfectly with the Required Permission sets | E5: Home page-->Coaching log tab | F5: Internal admin | G5: The admin is able to create a new coaching log which is populated by selecting role based log form | H5: working as Excepted | I5: Pass | J5: https://prutech.atlassian.net/browse/DOEECMS-1910 https://prutech.atlassian.net/browse/DOEECMS-2020
A6: 3 | E6: Coaching log--> new
A7: 4 | E7: Fill the required feilds Based on populated Role based log
A8: 5 | E8: Coaching log--> Instructional log
A9: 6 | E9: Coaching Log -->save --> Draft | G9: The admin is able to create a new coaching log which is populated by selecting role based log form
A10: 7 | B10: Verify that Admin is able to create a Goal in the Log | C10: Monitoring log /Coaching log | D10: Permissions Set Group -- Internal admin ECMS Instructional Coordinators ECMS Leadership Coaches ECMS Social Workers | E10: Coaching log-->Recently viewed | F10: Internal admin | G10: Internal administrators can conduct individual sessions, set goals, provide feedback, and collaborate on strategies for professional growth, using the coaching log to track the conversations and progress. ​ | H10: working as Excepted | I10: Pass
A11: 8 | E11: Coaching log-->select desired log link
A12: 9 | E12: Coaching log -->open-->Quick links
A13: 10 | E13: Coaching log-->Quick links-->Goals
A14: 11 | E14: Coaching log -->Goals--> new Goal
A15: 12 | E15: coaching log --> save
A16: 13 | B16: Verify that Internal administrators can edit coaching goals. | C16: Monitoring log /Coaching log | E16: Coaching log-->Recently Viewed log | F16: Internal admin | G16: The admin is able to edit goals from the log | H16: working as Excepted | I16: Pass | J16: https://prutech.atlassian.net/browse/DOEECMS-1905 https://prutech.atlassian.net/browse/DOEECMS-2038
A17: 14 | E17: Coaching log-->select desired log link
A18: 15 | E18: Coaching log -->open-->Quick links
A19: 16 | E19: Coaching log-->Quick links-->Goals
A20: 17 | E20: Coaching log -->Goals--> Edit
A21: 18 | E21: coaching log --> save
A22: 19 | B22: verify that Site Based Coaching Log Goals can be viewed by the internal administrator. | C22: Monitoring log /Coaching log | E22: Home page -> Site master | F22: Internal admin | G22: The admin is able to view Site Based Coaching Log Goals can be viewed by the internal administrator. | H22: working as Excepted | I22: Pass
A23: 20 | E23: Site master --> Required link -->open Site ID
A24: 21 | B24: Internal administrators can edit coaching log entries for instructional coaches and social workers to record their coaching experiences, strategies employed, and insights gained. From the edit screen, users can access the fidelity tool. ​ | C24: Monitoring log /Coaching log | E24: Home page-->Coaching log tab | F24: Internal admin | G24: The admin is able to select and edit the logs based their coaching experiences, strategies employed, and insights gained. From the edit screen, users can access the fidelity tool. ​ | H24: working as Excepted | I24: Pass | J24: https://prutech.atlassian.net/browse/DOEECMS-1906
A25: 22 | E25: Coaching log--> Recently Viewed
A26: 23 | E26: Coaching log--> Instructional log
A27: 24 | E27: Coaching Log --> Draft Status
A28: 25 | E28: Coaching log -->Edit button
A29: 26 | E29: coaching log -->Fidelity Tool -->based on experiences
A30: 27 | B30: Internal administrators can email coaching log entries to other ECMS users to review.​ | C30: Monitoring log /Coaching log | E30: Tab--> Coaching log | F30: Internal admin | G30: View the email draft screen that popped-up in the lower righthand corner. ​Enter your desired fields and begin composing your email. ​Add in Desired Fields from the Coaching Log Entry.​ ​ | H30: Not working as Excepted | I30: Fail | J30: https://prutech.atlassian.net/browse/DOEECMS-2037
A31: 28 | E31: coaching log --> open log hyper link
A32: 29 | E32: coaching log-->Activitytab
A33: 30 | E33: coaching log -->Click on Email
A34: 31 | E34: coaching log --> left corner compose mail
A35: 32 | E35: coaching log--> Merge fields
A36: 33 | E36: coaching log --> Send
A37: 34 | B37: Verify that Internal administrators may view previously created coaching logs and its details by sites. | C37: Monitoring log /Coaching log | E37: Homepage--> Site master site master-->site ID site ID -->Quick links-->view all -->coaching logs | F37: Internal admin | G37: Internal administrators are able to view previously created coaching logs and its details by sites. | H37: working as Excepted | I37: Pass
A38: 35 | E38: site master-->site ID
A39: 36 | E39: site ID -->Quick links-->view all -->coaching logs
A40: 37 | B40: Verify that Internal administrators may view and update Site Visit Frequency | C40: Monitoring log /Coaching log | E40: Home Page --> Site Master | F40: Internal admin | G40: The internal admin is able to View and visit the site Frequncy able to Update the Visit Frequncy | H40: working as Excepted | I40: Pass
A41: 38 | E41: Site master--> Open Site ID
A42: 39 | E42: Site Master--> ID -->Intensity Fields
A43: 40 | B43: The admin is able to View Sites I assigned to As Staff | C43: Monitoring log /Coaching log | E43: Home page-->Global search bar | F43: Internal admin | G43: The Admin is able to search the site staff with site | H43: working as Excepted | I43: Pass
A44: 41 | E44: Home page -->Site staff with Site-->Open -> View
A45: 42 | B45: Verify that admin is able to assign Leadership Coaches, Instructional Coordinators and Social Workers to Sites | C45: Monitoring log /Coaching log | E45: Homepage--> Site master | F45: Internal admin | G45: As an internal user I need to assign LeadershipCoaches, Instructional Coordinators and Social Workers to site | I45: Pass
A46: 43 | E46: site master-->site ID
A47: 44 | E47: site ID -->Quick links-->Site staff
A48: 45 | E48: Site staff --> new
A49: 46 | E49: Site Staff-->DOE internal-->select staff
A50: 47 | E50: Site staff -->Staff type = Site contact
A51: 48 | E51: site staff-> Designation -->which is Required
A52: 49 | E52: Click Save --> Return to site- the Staff is updated
A53: 50 | B53: Verify that admin is getting notified or getting alerts related log | C53: Monitoring log /Coaching log | E53: Home page ->Notification icon | F53: Internal admin | G53: In the Home page the admin is able to notifications on bell icon and below items to approve we can see the call alert related to Log | I53: Pass
A54: 51 | E54: Home page -->Open notification icon
A55: 52 | E55: Home page -->below Items to approve--> we get log call alerts
A56: 53 | B56: verify that admin is able to change the Log status from draft to complete | C56: Monitoring log /Coaching log | E56: Tab--> Coaching log | F56: Internal admin | G56: Internal admin is able move path from Dreft to Completed status | H56: working as Excepted | I56: Pass | J56: https://prutech.atlassian.net/browse/DOEECMS-2056 https://prutech.atlassian.net/browse/DOEECMS-2019 https://prutech.atlassian.net/browse/DOEECMS-1904
A57: 54 | E57: coaching log --> open log hyper link
A58: 55 | E58: coaching log--> From path --> mark status as complete
A59: 56 | B59: Select Site while creating Coaching Log | C59: Coaching Log | D59: Vendor admin should be Provisioned perfectly with the Required Permission sets | E59: Log in to Portal as FCCN User | F59: FCCN User | G59: Linked site should be searchable | H59: Unable to find site though it is linked to the Account and Contact. | I59: Fail | J59: https://prutech.atlassian.net/browse/DOEECMS-2036 https://prutech.atlassian.net/browse/DOEECMS-1948
A60: 57 | E60: Navigate to Coaching Logs → New → Education Specialist Log → Site
A61: 58 | B61: when a record is created/saved successfully then message should include proper id across all modules. | E61: Login to Portal as FCCN User | G61: Successfull message should include proper id | H61: working as Excepted | I61: Pass | J61: https://prutech.atlassian.net/browse/DOEECMS-2049
A62: 59 | E62: Navigate to Coaching log → Create/Edit → Save

Sheet Attendance
A1: =COUNT(A3:A97) -> 95 | B1: Total Test Cases
A2: Test Case ID | B2: Test Description/Title | C2: Module / Feature | D2: Functionality | E2: Test Type | F2: Preconditions | G2: Test Steps | H2: Test Data/ User | I2: Expected Result | J2: Actual Result | K2: Status | L2: Defect Retest reference
A3: 1 | B3: Vendor Admin should be able to create weekly attendance to the enrolled student | C3: Attendance | D3: Attendance/Weekly | E3: Positive | F3: Student should be enrolled under site and Approved by Enrollment Specialist. Enrollment should be in Approved status | G3: Login to ECMS portal as a Vendor | H3: Ravi Krishna | I3: Vendor Admin should be able to create weekly attendance to the enrolled student | J3: Working as Expected | K3: Pass
A4: 1 | C4: Attendance | D4: Attendance/Weekly | E4: Positive | G4: Click on Attendance → Weekly Attendance → Select EBC Site → Select JuniorKG Class | I4: User is able to select Junior KG Class | J4: Working as Expected | K4: In Design
A5: 1 | C5: Attendance | D5: Attendance/Weekly | E5: Positive | G5: Select Student name → Select Week | K5: In Design
A6: 1 | C6: Attendance | D6: Attendance/Weekly | E6: Positive | G6: Enter Status as Present --> Add 1st Check In and Check Out timings --> Save | K6: In Design
A7: 1 | B7: Vendor Admin should be able to create weekly attendance for 2nd Check In and Check Out | C7: Attendance | D7: Attendance/Weekly/2nd Check in and Check Out | E7: Positive | F7: Student should be enrolled under site and Approved by Enrollment Specialist. Enrollment should be in Approved status | G7: Login to ECMS portal as a Vendor | H7: Ravi Krishna | I7: 2nd Check In and Check Out timings should be saved | J7: Receiving successful message but record is not getting saved. | K7: Fail | L7: DOEECMS-1885
A8: 1 | C8: Attendance | D8: Attendance/Weekly/2nd Check in and Check Out | E8: Positive | G8: Click on Attendance → Weekly Attendance → Select EBC Site → Select JuniorKG Class | K8: In Design
A9: 1 | C9: Attendance | D9: Attendance/Weekly/2nd Check in and Check Out | E9: Positive | G9: Select Student name → Enter 2nd Check In and Check Out timings → Save | K9: In Design
A10: 1 | B10: Vendor Admin should be able to create Daily Attendance to the enrolled student | C10: Attendance | D10: Attendance/Daily | E10: Positive | F10: Student should be enrolled under site and Approved by Enrollment Specialist. Enrollment should be in Approved status | G10: Login to ECMS portal as a Vendor | H10: Ravi Krishna | I10: Only one entry should present for one day. | J10: Duplicate records getting created | K10: Fail | L10: DOEECMS-1889
A11: 1 | C11: Attendance | D11: Attendance/Daily | E11: Positive | G11: Click on Attendance → Daily Attendance → Select EBC Site → Select JuniorKG Class | K11: Pass
A12: 1 | C12: Attendance | D12: Attendance/Daily | E12: Positive | G12: Select Student name → Select date (eg Jan 15, 2026) | K12: Pass
A13: 1 | C13: Attendance | D13: Attendance/Daily | E13: Positive | G13: Enter Status as Present --> Add Check In and Check Out timings --> Save | K13: Pass
A14: 1 | B14: Vendor Admin should be able to submit Monthly Review | C14: Attendance | D14: Attendance/Monthly Review | E14: Positive | F14: Vendor should fill roaster for the particular month | G14: Login to ECMS portal as a Vendor | H14: Ravi Krishna | I14: Able to submit | J14: Working as Expected | K14: Pass
A15: 1 | C15: Attendance | D15: Attendance/Monthly Review | E15: Positive | G15: Click on Attendance → Daily Attendance → Select EBC Site → Select JuniorKG Class | K15: Pass
A16: 1 | C16: Attendance | D16: Attendance/Monthly Review | E16: Positive | G16: Select Attendance Month --> Attendance Class | K16: Pass
A17: 1 | C17: Attendance | D17: Attendance/Monthly Review | E17: Positive | G17: click checkbox --> submit | K17: Pass
A18: 1 | B18: Daily Attendance should not allow before Admission Date | C18: Attendance | D18: Attendance/Dates | E18: Negative | F18: Student should be enrolled under site and Approved by Enrollment Specialist. Enrollment should be in Approved status | G18: Login to ECMS portal as a Vendor | H18: Ravi Krishna | I18: System should not allow before Admission date (1/1/2026) | J18: The system allowed users to enter attendance before the student’s Admission Date(First Day of Attendance) | K18: Fail | L18: DOEECMS-1896
A19: 1 | G19: Click on Attendance → Daily Attendance → Select EBC Site → Select JuniorKG Class | K19: Pass
A20: 1 | G20: Select Student name → Select date (eg Dec 02, 2025) | K20: Pass
A21: 1 | G21: Fill Check In and Check Out timings and Save | K21: Pass
A22: 1 | B22: Internal Admin should have access to view Attendance Dashboards | C22: Attendance | D22: Attendance/Dashboards | E22: Positive | F22: Vendor Admit should submit Monthly review report | G22: Login to SF ECMS Application as Internal Admin | H22: Ravi Krishna | I22: Internal Admin should have access to view Attendance Dashboards | K22: Fail | L22: DOEECMS-1897
A23: 1 | C23: Attendance | D23: Attendance/Dashboards | E23: Positive | G23: Check Dashboards on Home Page | K23: Pass
A24: 1 | B24: Verify that admin is able to take attendance for enrollment is in submitted, approved and active in Status | C24: Attendance | D24: Attendance/Enrollment/Status | E24: Positive | F24: Enrollment should be in Submitted or Approved Or Active | G24: Log-->Portal | H24: Bunny | J24: Working as Expected | K24: Pass
A25: 1 | G25: Portal-->Attendance tab-->select Submitted Enrollment student
A26: 1 | G26: Portal--> Take Attendance | I26: Vendor Admin is able to take attendance for the enrollement submitted student
A27: 1 | B27: Attendance Date Should Not Be Before Student DOB | C27: Attendance | D27: Attendance/Dates | E27: Positive | G27: Login to Vendor Portal | I27: System should restrict attendance entry for dates before the Student DOB and display a validation error message. | J27: Attendance is saved successfully | K27: Pass | L27: https://prutech.atlassian.net/browse/DOEECMS-1982
A28: 1 | G28: Click on Attendance Tab --> Select weekly Attendance
A29: 1 | G29: Select Site --> class --> Select a student whose DOB is after First day of attendance
A30: 1 | G30: Fill attendance with check in/out days
A31: 1 | G31: Save the attendance | I31: Attendance is saved successfully
A32: 1 | B32: Verify record should not get saved if no status is given | C32: Attendance | D32: Attendance/Enrollment/Status | E32: Negative | G32: login portal → attendance tab | K32: Pass | L32: https://prutech.atlassian.net/browse/DOEECMS-1988
A33: 1 | G33: select student and try to take attendance without giving and with giving status as present don’t select the checkin and checkout time and click save | I33: It has to be restrict without filling the data it should not get save | J33: It was showing that record has sucessfully saved message | K33: Pass
A34: 1 | B34: Verify 2nd Check In/out fields Should be displayed in Backend in Attendance Information | C34: Attendance | D34: Attendance/Weekly/2nd Check in and Check Out | E34: Positive | G34: Login to Vendor Portal | I34: 2nd Check In/out fields should be displayed in Backend in Attendance Information, so that admin can check the data provided by vendor and make changes if required. | J34: 2nd Check In/out fields are not displayed in Backend in Attendance Information | K34: Pass | L34: https://prutech.atlassian.net/browse/DOEECMS-1983
A35: 1 | G35: Click on Attendance Tab --> Select weekly Attendance
A36: 1 | G36: Select Site --> class --> student --> Fill attendance with 2nd Check In/out fields
A37: 1 | G37: Save the attendance
A38: 1 | G38: Log into Backend as System Admin and check the student Contact --> Attendance Info
A39: 1 | G39: 2nd Check In/out fields are missing | I39: 2nd Check In/out fields should be displayed in Backend in Attendance Information, so that admin can check the data provided by vendor and make changes if required.
A40: 1 | B40: When accessing the Attendance module as a CBO Staff user on the portal, navigating to the Weekly Attendance feature results in an error message. | C40: Attendance | D40: Error Displayed When Accessing Weekly Attendance for CBO Staff User | G40: 1. Navigate to the Attendance module | I40: The Weekly Attendance page should load successfully without any errors. | J40: An error message is displayed on the Weekly Attendance page asking the user to refresh. Refreshing the page does not resolve the issue, and the error persists. | K40: Pass | L40: https://prutech.atlassian.net/browse/DOEECMS-1780
A41: 1 | G41: 2. Select the Weekly Attendance feature
A42: 1 | G42: 3. Observe the system behavior
A43: 1 | G43: 4. Refresh the page when prompted
A44: 1 | B44: CB Vendor User Unable to Access Monthly Review When Taking Attendance | C44: Attendance | D44: UI Broken for Monthly Attendance Review | G44: 1. Log in as a CBO Vendor user and have the test data set up for taking an attendance. 2. Navigate to Attendance. 3. Click on “Monthly Review” | I44: CB Vendor users should be able to click Monthly Review and access the monthly attendance summary without errors. | J44: The Monthly Review action does not work as expected for CBo Vendor user and a BLANK page is displayed with no options to select site/class/month. | K44: Pass | L44: https://prutech.atlassian.net/browse/DOEECMS-1834
A45: 1 | B45: CBO Vendor User Unable to Select Attendance Status (Present/Absent) in Weekly & Daily Attendance & 2nd Check in-Check Out issue | C45: Attendance | D45: Weekly & Daily Attendance & 2nd Check in-Check Out issue | G45: 1. Log in as a CBO Vendor User. | I45: 1. Daily and Weekly attendance - The Status field should function as a standard picklist and CBO Vendor users should be able to click the Status button and select a value (e.g., Present, Absent). 2. Weekly attendance - 2nd Checkin/Checkout shall work properly for the user. | J45: 1. Daily and Weekly attendance - The Status picklist is not functioning. The dropdown does not open when clicked. 2. Weekly attendance - When clicking on SHOW/HIDE 2nd Checkin and Checkout button, it is behaving abnormally. | K45: Pass | L45: https://prutech.atlassian.net/browse/DOEECMS-1847
A46: 1 | G46: 2. Navigate to Weekly Attendance or Daily Attendance.
A47: 1 | G47: 3. Select a Site.
A48: 1 | G48: 4. Select a Class.
A49: 1 | G49: 5. Select a Student from the roster.
A50: 1 | G50: 6. Attempt to click on the Status field to choose Present/Absent.
A51: 1 | G51: 7. Observe that the picklist does not open and no status can be selected.
A52: 1 | G52: 8. Additionally, for weekly attendance - the 2nd Checkin and Checkout button is behaving abnormally
A53: 1 | B53: The system allows users to enter attendance before the student’s Admission Date, which should not be permitted. | C53: Attendance | G53: 1.Log in as a vendor user. 2. Navigate to Weekly Attendance. 3. Select a Site → Class → Student. 4. Choose a week/month or year before the student’s admission date (e.g., a 2024 week for a student admitted on 12/24/2025). 5. Observe that attendance fields are editable even though they should not be. | I53: This is incorrect — attendance entries should only be allowed on or after the Admission Date. | J53: Student Admission Date: 12/24/2025 System still allows entering attendance for any dates before 12/24/2025. | K53: In Design | L53: https://prutech.atlassian.net/browse/DOEECMS-1849
A54: 1 | G54: 2. Navigate to Weekly Attendance.
A55: 1 | G55: 3. Select a Site → Class → Student.
A56: 1 | G56: 4. Choose a week/month or year before the student’s admission date (e.g., a 2024 week for a student admitted on 12/24/2025).
A57: 1 | G57: 5. Observe that attendance fields are editable even though they should not be.
A58: 1 | B58: When selecting a week that starts on a Monday, the calendar incorrectly displays attendance dates starting from the next day (Tuesday) and shifts the whole week forward by one day. | C58: Attendance | G58: 1.Log in as a vendor user. 2. Navigate to Weekly Attendance. 3. Select a Site → Class → Student. | J58: Working as Expected | K58: In Design | L58: https://prutech.atlassian.net/browse/DOEECMS-1850
A59: 1 | G59: 2. Navigate to Weekly Attendance. 3. Select a Site → Class → Student.
A60: 1 | G60: 4. Choose week starting Monday, June 17, 2024. 5. Observe the date range shown as June 18–June 22 instead of June 17–June 21 displaying incorrect days. | I60: The user is no longer able to select dates before to the Admission Date. When a Monday is selected as the week start date, the table now displays the correct dates and corresponding days.
A61: 1
A62: 1 | B62: Community Portal user assigned the ECMS Vendor Admin – External permission set group is unable to access the Attendance module in the community portal. Based on the assigned permission set, this user should have access to all applicable community modules, including Attendance. However, when attempting to access the Attendance module, the system displays an authorization error indicating insufficient permissions. This indicates a mismatch between the permission set assignment and actual access enforcement for the Attendance module. | C62: Attendance | F62: Community user is active User is assigned Permission Set Group: ECMS Vendor Admin – External User can successfully log into the ECMS Community Portal | G62: 1. Log in to Salesforce Setup 2. Navigate to Users | I62: A Community user with ECMS Vendor Admin – External permission set should be able to: Access the Attendance module View and perform Attendance-related actions as designed for Vendor Admin users No permission error should be displayed | J62: User receives an error message: “You do not have permission to access the Attendance module.” Attendance module does not load | K62: In Design | L62: https://prutech.atlassian.net/browse/DOEECMS-1913
A63: 1 | G63: 2. Navigate to Users 3. Open the affected Community User record
A64: 1 | G64: Verify Permission Set Group Assignment: ECMS Vendor Admin – External is assigned 5. Log in as the same user via the ECMS Community Portal
A65: 1 | G65: 6. Navigate to the Attendance module 7. Click on Attendance | I65: A Community user with ECMS Vendor Admin – External permission set should be able to: Access the Attendance module View and perform Attendance-related actions as designed for Vendor Admin users No permission error should be displayed
A66: 1 | B66: Unable to submit ‘Report Absence’ for an Enrolled student. | C66: Attendance | G66: Login to ECMS Portal as a Vendor user Go to Submitted Enrollments → Open any record → Click On top right cornerdropdown | J66: Working as Expected | K66: In Design | L66: https://prutech.atlassian.net/browse/DOEECMS-1966
A67: 1 | G67: Report Absence → Fill The details and submit. | I67: Vendor should be able to Report Absence for an Enrolled student.
A68: 1 | B68: Attendance Date Should Not Be Before Student DOB | C68: Attendance | G68: 1. Login to Vendor Portal 2. Click on Attendance Tab --> Select weekly Attendance 3. Select Site --> class --> Select a student whose DOB is after First day of attendance | J68: Attendance is saved successfully | K68: In Design | L68: https://prutech.atlassian.net/browse/DOEECMS-1982
A69: 1 | G69: Click on Attendance Tab --> Select weekly Attendance 3. Select Site --> class --> Select a student whose DOB is after First day of attendance
A70: 1 | G70: 4. Fill attendance with check in/out days 5. Save the attendance | I70: System should restrict attendance entry for dates before the Student DOB and display a validation error message.
A71: 1 | B71: ECMS Attendance for Vendors - View Report – Current Month Attendance by Seat Type and Class Not Displayed in Correct Position. | C71: Attendance | D71: Attendance dashboard | G71: 1.Log into Test Org as ECMS internal Admin 2.Navigate to the ECMS home screen. | I71: View report for Current Month Attendance by Seat Type and Class should be displayed in Correct Position. | J71: View report for Current Month Attendance by Seat Type and Class not displayed in Correct Position. | K71: In Design | L71: https://prutech.atlassian.net/browse/DOEECMS-1994
A72: 1 | G72: Click on the nine dots on the top navigation bar and type “Dashboards". 4.Click on “Dashboards”.
A73: 1 | G73: Click “All Dashboards” in the leftmost navigation pane. 6.Click on, “ECMS Attendance for Vendors.”
A74: 1 | G74: .View the “Current Month Attendance by Seat Type” dashboard. 8.At the end , View report is displayed for Class.
A75: 1 | G75: 9.View the “Current Month Attendance by Class” dashboard. 10.At the end, View report is displayed for Seat Type. | I75: View report for Current Month Attendance by Seat Type and Class should be displayed in Correct Position.
A76: 1 | B76: ECMS Attendance for Vendors - View Report – Current Month Attendance by Seat Type is not Displayed as Expected | C76: Attendance | D76: Attendance dashboard | G76: Log into Test Org as ECMS internal Admin Navigate to the ECMS home screen. | J76: View report for Current Month Attendance by Seat Type is not showing correct data | K76: In Design | L76: https://prutech.atlassian.net/browse/DOEECMS-1995
A77: 1 | G77: Click on the nine dots on the top navigation bar and type “Dashboards". Click on “Dashboards”.
A78: 1 | G78: Click “All Dashboards” in the leftmost navigation pane. Click on, “ECMS Attendance for Vendors.”
A79: 1 | G79: View the “Current Month Attendance by Seat Type” dashboard. Click on View Report (Current Month Attendance by Seat Type) Hyperlink | I79: When clicked on View report for Current Month Attendance by Seat Type, correct Information and Graph related to Seat type should be displayed
A80: 1 | B80: Attendance with Closure status is saving Check in/Out dates in the backend | C80: Attendance | G80: Log into Test Org as Vendor user Click on Attendance --> Daily/ Weekly Attendance | J80: When Attendance is filled with Closure status, check in/out time is being saved | K80: In Design | L80: https://prutech.atlassian.net/browse/DOEECMS-1997
A81: 1 | G81: Daily attendance --> Select Site --> Class --> Student --> Fill attendance status as present initially
A82: 1 | G82: Fill check in/out dates and now change the status to closure
A83: 1 | G83: Save the Attendance In case of Daily Attendance --> Check in/out timings are displayed in Vendor login also after saving with closure status
A84: 1 | G84: In case of Weekly Attendance --> Check in/out timings are erased in Vendor login after saving with closure status
A85: 1 | G85: Go back to Backend and check in student contact --> Attendance record --> for closure status day attendance, check in/check out timings are displayed. | I85: When Attendance is filled with Closure status, check in/out time fields should be blank in all areas.
A86: 1 | B86: When we report attendance for a student giving absence report before the first day of attendance | C86: Attendance | D86: Report absence | G86: Login portal-->Enrollments tab Select submitted enrollments from the leftmost dropdown select enrollment and from right corner dropdown select report absence Give the date before the first day of attendance and submit observe the behavior | I86: It should restrict the day before first day of attendance give an error message related issue | J86: The report absence get added to the record without displaying an error message and restriction | K86: In Design | L86: https://prutech.atlassian.net/browse/DOEECMS-1998
A87: 1 | B87: Improper Check-In/Check-Out Time Validation issue in Daily Attendance | C87: Attendance | G87: Click on Attendance --> Daily Attendance Daily attendance --> Select Site --> Class --> Student --> Fill attendance with Invalid time zone Fill 1st Check in : 6AM 1st Check out : 9AM 2nd Check in : 7AM 2nd Check out: 9AM System is saving attendance with improper check in/out timings. | I87: 1st Check in/out timings should be less than the 2nd Check in/out timings. | J87: System is saving attendance with improper check in/out timings. | K87: In Design | L87: https://prutech.atlassian.net/browse/DOEECMS-2007
A88: 1 | B88: EDY Attendance Validation Triggered for Non-Admission Dates | C88: Attendance | F88: Timesheet is mandatory for all EDY Students | G88: Log into Test Org as Vendor user Click on Attendance --> Daily/Weekly Attendance | J88: Getting EDY validation when not needed | K88: In Design | L88: https://prutech.atlassian.net/browse/DOEECMS-2008
A89: 1 | G89: Weekly attendance --> Select Site --> Class --> Student --> Fill the data
A90: 1 | G90: Admission date for student is Feb 10th, 2026 - so weekly attendance starts from Feb 9th to Feb 13th
A91: 1 | G91: Feb 9th will be disabled ad admission date is Feb 10th After filling attendance from 10th to 13th and clicked on save, getting validation for EDY as Error notification. | I91: EDY validation should come to days which are included from date of admission
A92: 1 | B92: User able to save Weekly Attendance without adding CheckIn/CheckOut timings | C92: Attendance | G92: Login in to portal as Vendor User Click on Attendance tab → Weekly Attendance → Select Site → Class → Student | J92: Record saved sucessfully without any error message | K92: In Design | L92: https://prutech.atlassian.net/browse/DOEECMS-2017
A93: 1 | G93: Select week and add Status (Present/Absent/Closure) –> Click on Save | I93: System should throw error message to enter CheckIn/CheckOut timings
A94: 1 | B94: Student’s ‘First Day of Attendance’ was from 7/1/2025. So User wants to review Monthly Attendance. | C94: Attendance | D94: User able to see only few months on Monthly Review | G94: Login in to portal as Vendor User Click on Attendance tab → Monthly Review → Select Site | J94: July month is not showing | K94: In Design | L94: https://prutech.atlassian.net/browse/DOEECMS-2018
A95: 1 | G95: Attendance Month → Search for July month is not showing | I95: System should display July month as Student’s ‘First Day of Attendance’ was from 7/1/2025.
A96: 1 | B96: Monthly Attendance - Class Name is missing when editing the not Filled days before Certify | C96: Attendance | G96: Log into Test Org as Vendor user Click on Attendance --> Monthly Attendance | J96: Monthly Attendance - Class Name is missing when editing the not Filled days before Certify | K96: In Design | L96: https://prutech.atlassian.net/browse/DOEECMS-2023
A97: 1 | G97: Weekly attendance --> Select Site --> Month Click on Edit to fill the pending attendance | I97: Monthly Attendance - Class Name should be visible when editing the not Filled days
G98: In View, Class Name field data is missing

Sheet Budget
A2: Test Case ID | B2: Module / Feature | C2: Functionality | D2: Test Type | E2: Test Scenario | F2: Preconditions | G2: Test Steps | H2: Test Data | I2: Expected Result | J2: Status | K2: Priority | L2: Defect Retest reference
A3: 1 | B3: Budget | C3: Budget/NewBudget | D3: Positive | E3: Vendor Admin (Experience User) Should be able create a new Budget from Site > ECMS Contract | F3: User is an Experience Cloud user (active) tied to a Contact under the Vendor Account. User is assigned to ECMS Vendor Admin External Permission Assignment Group (as you confirmed). Vendor Account has: At least one active Site visible to the vendor user in portal At least one ECMS Contract linked/available for that Site (and in valid FY/status to allow budgeting) User can successfully log into the ECMS Portal. | G3: Log in to ECMS Portal as Experience user (Vendor Admin). | I3: Confirm user is successfully logged in | J3: Reviewed Completed | L3: DOEECMS-1867
A4: 2 | B4: Budget | C4: Budget/NewBudget | D4: Positive | G4: From the portal menu, open Site. | I4: Confirm site is launched successfully | J4: Reviewed Completed
A5: 3 | B5: Budget | C5: Budget/NewBudget | D5: Positive | G5: Select a valid Site record. | I5: confirm system accept user input | J5: Reviewed Completed
A6: 4 | B6: Budget | C6: Budget/NewBudget | D6: Positive | G6: Click ECMS Contract (related section / tab / related list). | I6: Verify system should show all related contracts | J6: Reviewed Completed
A7: 5 | B7: Budget | C7: Budget/NewBudget | D7: Positive | G7: Open the relevant ECMS Contract record. | I7: Verify ECMS contract record is open | J7: Reviewed Completed
A8: 6 | B8: Budget | C8: Budget/NewBudget | D8: Positive | G8: Click Create New Budget. | I8: System should open the New Budget page / Budget creation flow and allow the user to: Select FY / Site / Contract Type (as applicable) Save Budget as Draft See Budget record created and visible under Budgets list Expected Outcome: Budget creation screen loads and a new Budget record can be created. | J8: Reviewed Completed
A9: 7 | B9: Budget | C9: Budget/NewBudget | D9: Positive | E9: Site Manager (Experience User) Should be able create a new Budget from Site > ECMS Contract | F9: User is an Experience Cloud user (active) tied to a Contact under the Vendor Account. User is assigned to ECMS Site Manager External Permission Assignment Group (as you confirmed). Vendor Account has: At least one active Site visible to the vendor user in portal At least one ECMS Contract linked/available for that Site (and in valid FY/status to allow budgeting) User can successfully log into the ECMS Portal. | G9: Log in to ECMS Portal as Experience user (Site Manager). | I9: Successfully logged in | J9: Reviewed Completed
A10: 8 | B10: Budget | C10: Budget/NewBudget | D10: Positive | G10: From the portal menu, open Site. | I10: Confirm user land on the site | J10: Reviewed Completed
A11: 9 | B11: Budget | C11: Budget/NewBudget | D11: Positive | G11: Select a valid Site record. | I11: Confirm valid site record is selected | J11: Reviewed Completed
A12: 10 | B12: Budget | C12: Budget/NewBudget | D12: Positive | G12: Click ECMS Contract (related section / tab / related list). | I12: Confirm user land on related list tab | J12: Reviewed Completed
A13: 11 | B13: Budget | C13: Budget/NewBudget | D13: Positive | G13: Open the relevant ECMS Contract record. | I13: Confirm relevant contract record is selected | J13: Reviewed Completed
A14: 12 | B14: Budget | C14: Budget/NewBudget | D14: Positive | G14: Click Create New Budget. | I14: confirm user land on budget page | J14: Reviewed Completed
A15: 13 | B15: Budget | C15: Budget/NewBudget | D15: Positive | E15: When a vendor submits a budget for approval or the budget is approved by OA and sent to OD for next level approval, the Items to Approve component on the ECMS Home Page should display a single entry | G15: Submit the budget using Submit Budget (for vendor portal) or Approve Budget as OA AND Sent for approval to OD. | I15: Confirm budget is sent to approval | J15: Reviewed Completed | L15: DOEECMS-1804
A16: 14 | B16: Budget | C16: Budget/NewBudget | D16: Positive | G16: Log in as an Internal DECE user (OA/OD). | I16: Confirm user is succesfully logged in | J16: Reviewed Completed
A17: 15 | B17: Budget | C17: Budget/NewBudget | D17: Positive | G17: Navigate to the Home Page. | I17: Confirm user lands on home page | J17: Reviewed Completed
A18: 16 | D18: Positive | G18: Review the Items to Approve component. | I18: Only one approval entry should appear for each budget submitted. The component should display a single actionable record corresponding to the submitted budget. | J18: Reviewed Completed
A19: 17 | B19: Budget | C19: Amend Budget with Contact Change | D19: Positive | E19: Verify user should be able to change POC Contact when Amending a Budget | F19: Vendor user has valid Community Portal access and required permissions to amend budgets. An existing Budget is in status Approved by DOE. An Invoice exists for the same Site/Contract/Budget context and is currently in Saved status (not submitted). Budget is visible to the Vendor user in the Community Portal. | G19: Login to ECMS Community Portal as Vendor Management / Vendor Admin user. | I19: Accept the New Contact selection, Persist the selected Contact for the amendment context, and Allow the user to proceed to the next step of the amendment flow (continue amendment of the budget). | J19: Reviewed Completed
A20: 18 | D20: Positive | G20: Navigate to Budgets. | I20: lands on budget list | J20: Reviewed Completed
A21: 19 | D21: Positive | G21: Open an existing Budget that is Approved and has an Invoice created in Saved status. | I21: and has an Invoice created in Saved status. | J21: Reviewed Completed
A22: 20 | D22: Positive | G22: Click Amend Budget. | I22: Budget is now open in amend and new Budget ID is generated | J22: Reviewed Completed
A23: 21 | D23: Positive | G23: In the amendment flow, navigate to the Budget Information screen. | I23: confirm budget information screen should display | J23: Reviewed Completed
A24: 22 | D24: Positive | G24: Select the radio button New Contact. | I24: Confirm system allow user action | J24: Reviewed Completed
A25: 23 | D25: Positive | G25: Choose a new Contact from the list (lookup/picklist). | I25: Confirm system allow user to select new contact from the list | J25: Reviewed Completed
A26: 24 | D26: Positive | G26: Click Next. | I26: confirm user should be able to change the contact | J26: Reviewed Completed
A27: 25 | D27: Positive | E27: Verify Budget deletion by System Admin | F27: System Admin should be logged into the system | G27: Navigate to required budget in SF and click on "delete" from the action dropdown. | I27: Delete budget prompt gets displayed | J27: Reviewed Completed
G28: Click on "Delete" on the Delete Budget prompt | I28: Budget gets deleted and is no longer available in the system | J28: Reviewed Completed
E29: Verify non-system admin can't delete a budget | F29: Non- System Admin should be logged into the system | G29: Navigate to required budget in SF and click on the action dropdown in the right. | I29: Delete option should not be displayed in the dropdown | J29: Reviewed Completed
A30: 26 | B30: Budget | C30: Update Line Items | D30: Positive | E30: Verify Vendor admin should be able to update line items | F30: Budget should be saved and available | G30: Log in as a Vendor user with ECMS Budgets – External permission set. | I30: confirm user is successfully logged in | J30: Reviewed Completed | L30: DOEECMS-1802
A31: 27 | B31: Budget | C31: Update Line Items | D31: Positive | G31: Navigate to Budgets. | I31: Confirm budget page displays | J31: Reviewed Completed
A32: 28 | B32: Budget | C32: Update Line Items | D32: Positive | G32: Open any Saved Budget record. | I32: confirm user should be able to open budget | J32: Reviewed Completed
A33: 29 | B33: Budget | C33: Update Line Items | D33: Positive | G33: Click the dropdown in the top‑right and select Update Line Items. | I33: confirm user should be able to update line items | J33: Reviewed Completed
A34: 30 | B34: Budget | C34: Update Line Items | D34: Positive | G34: Observe system behavior. | I34: Vendor should be able to add/edit line items | J34: Reviewed Completed
A35: 31 | B35: Budget | C35: Create/Edit | E35: Verify External User shoud be able to Create Budget | F35: User is an Experience Cloud user (active) tied to a Contact under the Vendor Account. User is assigned required Permission Assignment Group . Vendor Account has: At least one active Site visible to the vendor user in portal At least one ECMS Contract linked/available for that Site (and in valid FY/status to allow budgeting) User can successfully log into the ECMS Portal. | G35: 1)Navigate to Budgets and click Create New Budget | I35: Budget page will open | J35: Reviewed Completed
G36: 2)Enter required budget details | I36: Budget details will get entered | J36: Reviewed Completed
G37: 3)Click Save | I37: A confirmation message should be displayed and the budget status should be set to the expected initial status (e.g., Draft/Saved) The budget record should display the selected Contact and Total Amount | J37: Reviewed Completed
E38: Amend an existing budget-Update/contact an amount | F38: User is logged in into the system and a submitted budget is available for amendment. | G38: View the budget details page and click on Amend Budget | I38: Amend budget screen will open | J38: Ready
G39: Select/change the contact as desired | I39: Contact gets selected. | J39: Ready
A40: 32 | G40: Update other data(line items, classes and documents) as required and click on next | I40: Amended budget should get saved | J40: Ready
G41: Check Amended Level. “A” indicates one amendment; “B” indicates two amendments; “C” indicates three amendments. Click the links to any related budget to view the detailed record for that prior version. | I41: Level should be accurate | J41: Ready
A45: 33 | E45: Verify Amount Validation in the budget during amendment | G45: Given I am amending a budget When I enter an invalid amount (e.g., negative value, exceeds allowed limits, or invalid format) And I attempt to save the amendment Then the system should prevent the save action And display a clear validation message explaining the rule violation | J45: In Design
A46: 34 | E46: Verify Amendment of a budget is blocked based on budget status | G46: Given I am viewing a budget that is not eligible for amendment (e.g., Submitted, Approved, or Locked) When I attempt to amend the budget Then the Amend Budget option should not be available Or the system should block the action with a clear explanatory message | J46: In Design
A47: 35 | E47: Verify Cancelling and amendment of a budget doesn't impact the original budget | G47: Given I have initiated an amendment and modified the contact and amount When I cancel the amendment or exit without saving Then the original budget should remain unchanged And no amendment record should be created | J47: In Design
A48: 36 | E48: Verify that if a budget is in approval queue, then a new budget cannot be created | F48: A Budget in approval queue already exists for: • Same Site • Same Fiscal Year | G48: Login to the portal and attempt to create a budget | I48: Message is received "You already have a budget in the status of "Pending Approval" for the selected Contract Type and the Fiscal year: "Budget number" Please click Next to be redirected to the Saved Budget. | J48: Reviewed Completed
A49: 37 | B49: Budget | C49: New Budget - Negative Scenario | E49: Verify a new Budget is created without selecting active Site | G49: Log in to ECMS Portal as Experience user In Home screen, Click on Create Budget Button --> New Without selecting atlease one site, click on Next | I49: There should be a validation error message and system should not allow for further step | J49: Reviewed Completed
A50: 38 | B50: Budget | C50: Saved Budget - Negative Scenario | E50: Submit a saved Budget without adding classes for Approval | G50: Log in to ECMS Portal as Experience user In Home screen, Click on Create Budget Button --> New Create a Budget without adding classes Open any saved Budget and submit budget for Approval System should restrict Vendor from submission and display validation message to add classes | I50: System should restrict Vendor from submission and display validation message to add classes | J50: Reviewed Completed
A51: 39 | B51: Budget | C51: Saved Budget - Negative Scenario | E51: Submit a saved Budget without Updating line items for Approval | G51: Log in to ECMS Portal as Experience user In Home screen, Click on Create Budget Button --> New Create a Budget with classes Open any saved Budget and submit budget for Approval System should restrict Vendor from submission and display validation message to update line items | I51: System should restrict Vendor from submission and display validation message to update line items | J51: Reviewed Completed
A52: 40 | B52: Budget | C52: New Budget | E52: Verify that if a budget is already created and in saved status, try to create one more Budget with same site | G52: Given I have an existing budget that is in saved status When I select New Budget And choose a same site with which already a budget is created Then the system should prevent the Duplicate Budget creation | I52: System should prevent the Duplicate Budget creation | J52: Reviewed Completed
A53: 43 | B53: Budget | E53: Verify New contact selection should proceed for approved budget with saved invoice during amendement of a budget | F53: Vendor user has valid Community Portal access and required permissions to amend budgets. An existing Budget is in status Approved by DOE. An Invoice exists for the same Site/Contract/Budget context and is currently in Saved status (not submitted). Budget is visible to the Vendor user in the Community Portal. | G53: Login to ECMS Community Portal as Vendor Management / Vendor Admin user. | J53: Reviewed Completed
A54: 44 | B54: Budget | G54: Navigate to Budgets. | J54: Reviewed Completed
A55: 45 | B55: Budget | G55: Open an existing Budget that is Approved and has an Invoice created in Saved status. | J55: Reviewed Completed
A56: 46 | B56: Budget | G56: Click Amend Budget. | J56: Reviewed Completed
A57: 47 | B57: Budget | G57: In the amendment flow, navigate to the Budget Information screen. | J57: Reviewed Completed
A58: 48 | B58: Budget | G58: Select the radio button New Contact. | J58: Reviewed Completed
A59: 49 | B59: Budget | G59: Choose a new Contact from the list (lookup/picklist). | J59: Reviewed Completed
A60: 50 | B60: Budget | G60: Click Next. | I60: Accept the New Contact selection, Persist the selected Contact for the amendment context, and Allow the user to proceed to the next step of the amendment flow (continue amendment of the budget). | J60: Reviewed Completed | L60: DOEECMS-1880
E61: Budget Approvals-> OD is not able to approve/reject/reassign budgets unless OA has approved them | F61: User is logged into the system as an Operations Director. Budget is pending for OA's approval in the system | G61: 1)Login as a vendor admin to portal. | I61: User is logged into the system | J61: Reviewed Completed
A62: 51 | B62: Budget | C62: Budget | G62: 2)Create and Submit a budget for approval in “Pending Approval” Status | I62: Budget should get created | J62: Reviewed Completed
A63: 52 | B63: Budget | G63: 3)Login to SF and see that the budget is assigned to Operations Analyst | I63: Assignment is visible | J63: Reviewed Completed
A64: 53 | B64: Budget | G64: 4)Login as Operations Director Internal user in SF-> ECMS app | I64: Operations director is logged in | J64: Reviewed Completed
A65: 54 | B65: Budget | G65: 5)Go to Approvals History → Budget record → ‘Approval Request’ page | I65: Approve/Reject/Reassign buttons are not available. OD shall be able see the custom buttons on approval record to Approve, Reject or Reassign ONLY after OA approval is completed | J65: Reviewed Completed | L65: DOEECMS-1724
E66: An ECMS Internal User(OA) can enter comments on a saved Budget so vendors are informed of necessary edits to the budget. | F66: A saved budget is available | G66: 1) Login to Salesforce as OA | I66: User is logged into the system | J66: Reviewed Completed
A67: 55 | B67: Budget | G67: 2) Navigate to the SAVED budget you want to enter comments for | I67: Budget page will open | J67: Reviewed Completed
A68: 56 | B68: Budget | G68: 3) Click on “Comments” tab | I68: Comments section will open | J68: Reviewed Completed
A69: 57 | B69: Budget | G69: 4) Select setting for “To” as “All with access” | I69: Setting gets selected | J69: Reviewed Completed
A70: 58 | B70: Budget | G70: 5) Post a comment. Click Share | I70: 1) The comment gets saved in the system and is visible in the Comments section. 2) Vendor can login into the portal and see the comment listed in the budget record. | J70: Reviewed Completed
E71: An ECMS Internal User(OD) can enter comments on a saved Budget so vendors are informed of necessary edits to the budget. | F71: A saved budget is available | G71: 1) Login to Salesforce as OD | I71: User is logged into the system | J71: Reviewed Completed
A72: 59 | B72: Budget | G72: 2) Navigate to the SAVED budget you want to enter comments for | I72: Budget page will open | J72: Reviewed Completed
A73: 60 | B73: Budget | G73: 3) Click on “Comments” tab | I73: Comments section will open | J73: Reviewed Completed
A74: 61 | B74: Budget | G74: 4) Select setting for “To” as “All with access” | I74: Setting gets selected | J74: Reviewed Completed
A75: 62 | B75: Budget | G75: 5) Post a comment. Click Share | I75: 1) The comment gets saved in the system and is visible in the Comments section. 2) Vendor can login into the portal and see the comment listed in the budget record. | J75: Reviewed Completed
E76: An ECMS Internal User(OA) can enter comments on a "pending for approval" Budget so vendors are informed of necessary edits to the budget. | F76: A budget is available in the "pending for approval" status | G76: 1) Login to Salesforce as OA | I76: User is logged into the system | J76: Reviewed Completed
A77: 63 | B77: Budget | G77: 2) Navigate to the budget in PENDING APPROVAL status, that you want to enter comments for | I77: Budget page will open | J77: Reviewed Completed
A78: 64 | G78: 3) Click on “Comments” tab | I78: Comments section will open | J78: Reviewed Completed
A79: 65 | G79: 4) Select setting for “To” as “All with access” | I79: Setting gets selected | J79: Reviewed Completed
A80: 66 | G80: 5) Post a comment. Click Share | I80: 1) The comment gets saved in the system and is visible in the Comments section. 2) Vendor can login into the portal and see the comment listed in the budget record. | J80: Reviewed Completed
E81: An ECMS Internal User(OD) can enter comments on a "pending for approval" Budget so vendors are informed of necessary edits to the budget. | F81: A budget is available in the "pending for approval" status | G81: 1) Login to Salesforce as OD | I81: User is logged into the system | J81: Reviewed Completed
A82: 67 | G82: 2) Navigate to the budget in PENDING APPROVAL status, that you want to enter comments for | I82: Budget page will open | J82: Reviewed Completed
A83: 68 | G83: 3) Click on “Comments” tab | I83: Comments section will open | J83: Reviewed Completed
A84: 69 | G84: 4) Select setting for “To” as “All with access” | I84: Setting gets selected | J84: Reviewed Completed
A85: 70 | G85: 5) Post a comment. Click Share | I85: 1) The comment gets saved in the system and is visible in the Comments section. 2) Vendor can login into the portal and see the comment listed in the budget record. | J85: Reviewed Completed | L85: DOEECMS-1924
E86: An ECMS Internal User(OA) can enter comments on a "REJECTED BY DOE" Budget so vendors are informed of necessary edits to the budget. | F86: A budget is available in the "rejected by DOE" status | G86: 1) Login to Salesforce as Operations Analyst | I86: User is logged into the system | J86: Reviewed Completed
A87: 71 | G87: 2) Navigate to the budget in REJECTED BY DOE status, that you want to enter comments for | I87: Budget page will open | J87: Reviewed Completed
A88: 72 | G88: 3) Click on “Comments” tab | I88: Comments section will open | J88: Reviewed Completed
A89: 73 | G89: 4) Select setting for “To” as “All with access” | I89: Setting gets selected | J89: Reviewed Completed
A90: 74 | G90: 5) Post a comment. Click Share | I90: 1) The comment gets saved in the system and is visible in the Comments section. 2) Vendor can login into the portal and see the comment listed in the budget record. | J90: Reviewed Completed
E91: An ECMS Internal User(OD) can enter comments on a "REJECTED BY DOE" Budget so vendors are informed of necessary edits to the budget. | F91: A budget is available in the "rejected by DOE" status | G91: 1) Login to Salesforce as OD | I91: User is logged into the system | J91: Reviewed Completed
A92: 75 | G92: 2) Navigate to the the budget in REJECTED BY DOE status, that you want to enter comments for | I92: Budget page will open | J92: Reviewed Completed
A93: 76 | G93: 3) Click on “Comments” tab | I93: Comments section will open | J93: Reviewed Completed
A94: 77 | G94: 4) Select setting for “To” as “All with access” | I94: Setting gets selected | J94: Reviewed Completed
A95: 78 | G95: 5) Post a comment. Click Share | I95: 1) The comment gets saved in the system and is visible in the Comments section. 2) Vendor can login into the portal and see the comment listed in the budget record. | J95: Reviewed Completed
E96: An ECMS Internal User(OA) can enter comments on an "amended" Budget so vendors are informed of necessary edits to the budget. | F96: A budget is available in the "Amended" status | G96: 1) Login to Salesforce as Operations Analyst | I96: User is logged into the system | J96: Reviewed Completed
A97: 79 | G97: 2) Navigate to the budget in AMENDED BUDGET status, that you want to enter comments for | I97: Budget page will open | J97: Reviewed Completed
A98: 80 | G98: 3) Click on “Comments” tab | I98: Comments section will open | J98: Reviewed Completed
A99: 81 | G99: 4) Select setting for “To” as “All with access” | I99: Setting gets selected | J99: Reviewed Completed
A100: 82 | G100: 5) Post a comment.Click Share | I100: 1) The comment gets saved in the system and is visible in the Comments section. 2) Vendor can login into the portal and see the comment listed in the budget record. | J100: Reviewed Completed
E101: An ECMS Internal User(OD) can enter comments on an "amended" Budget so vendors are informed of necessary edits to the budget. | F101: A Budget is available with status: AMENDED BUDGET | G101: 1) Login to Salesforce as OD | I101: User is logged into the system | J101: Reviewed Completed
A102: 83 | G102: 2) Navigate to budget in AMENDED BUDGET status, that you want to enter comments for | I102: Budget page will open | J102: Reviewed Completed
A103: 84 | G103: 3) Click on “Comments” tab | I103: Comments section will open | J103: Reviewed Completed
A104: 85 | G104: 4) Select setting for “To” as “All with access” | I104: Setting gets selected | J104: Reviewed Completed
...

Sheet Incident
A1: =COUNT(A5:A51) -> 36 | B1: Total # of Test cases
A3: Test Case ID | B3: Test Description/Title | C3: Module / Feature | D3: Functionality | E3: TestType | F3: Preconditions | G3: Test Steps | H3: Test Data/ User | I3: Expected Result | J3: Actual outcome | K3: Status | L3: Defect Retest reference
B4: Verify Vendor Admin can see Incident report Tab on external portal | C4: Incident Report | E4: Positive | G4: Login as a Vendor Admin user | I4: Vendor successfully logged in | K4: Pass
A5: 1 | C5: Incident Report | E5: Positive | G5: Navigate to “More” menu tab | I5: Report Incident” option is visible and clickable | K5: Pass
A6: 2 | B6: Verify - Report Incident should not be visible for Non Admin user | C6: Incident Report | E6: Positive | G6: Login as a Non Admin user Navigate to “More” menu tab | H6: ECMS Create & Update Enrollment ECMS External Manage Budgets ECMS Manage Budgets | I6: Report Incident” option should not be visible. | K6: Pass
A7: 3 | B7: Verify Vendor Admin should be able to submit an incident and Verify Subject, Category, Concern, Incident Date are marked required | C7: Incident Report | E7: Positive | G7: Login as a Vendor Admin user | I7: Vendor successfully logged in | K7: Pass
A8: 4 | C8: Incident Report | E8: Positive | G8: Navigate to “More” menu tab | I8: Report Incident” option is visible and clickable | K8: Pass
A9: 5 | C9: Incident Report | E9: Positive | G9: Click Submit | I9: Confirm system should respond with an error message " These required fields must be completed: Concern, Incident Date, Subject" | K9: Pass
A10: 6 | C10: Incident Report | E10: Positive | G10: Populate all the require fields and upload a PDF document | I10: Confirm document is uploaded successfully | K10: Pass
A11: 7 | B11: Verify Incident Intake Team member should be able to create an Incident in Salesforce. | C11: Incident Report | E11: Positive | G11: Navigate to Incident Case Tab Verify default status = New Navigate to Incident Case Tab CLICK + | I11: Confirm new page is displayed | K11: Pass
A12: 8 | C12: Incident Report | E12: Positive | G12: Click Save | I12: Confirm A new incident case is created successfully | K12: Pass
A13: 9 | B13: Verify System should notify Team member if escalation level 1 case is not updated within last 24 hrs. | C13: Incident Report | D13: Case Notification | E13: Positive | K13: In Design
A14: 10 | B14: Verify a new incident case should be created when send via email | E14: Positive | K14: In Design
A15: 11 | B15: Incident Management Team Member can select a status stage on Path | C15: Incident Report | D15: Update | E15: Positive | F15: User has Incident Management Team Member access. An Incident Case record exists and is accessible to the user. Path is configured on the Case object for the Status field | G15: Log in as an Incident Management Team Member. | H15: Incident Management Team Member | K15: In Design
A16: 12 | C16: Incident Report | D16: Update | E16: Positive | G16: Open any Incident Case record. | K16: In Design
A17: 13 | C17: Incident Report | D17: Update | E17: Positive | G17: On the Path component, click a different status stage than the current one. | I17: The selected stage becomes highlighted/selected on the Path (ready to be saved). No errors occur. | K17: In Design
A18: 14 | B18: Escalation Level field is visible and populated for Incident Management Team Member on Incident Case | C18: Incident Report | E18: Positive | F18: An Incident Case record exists with Escalation Level expected to be populated The Incident Case record is accessible to both: System Administrator Incident Management Team Member The test user for Incident Management Team Member is assigned the correct profile/permission sets. Test Data | G18: Log in as System Administrator. | H18: System Administrator. | K18: In Design
A19: 15 | C19: Incident Report | E19: Positive | G19: Navigate to Incident Cases and open the test Incident Case record. | K19: In Design
A20: 16 | C20: Incident Report | E20: Positive | G20: Verify the Escalation Level field is visible on the page and note the value displayed. | K20: In Design
A21: 17 | C21: Incident Report | E21: Positive | G21: Log out. | K21: In Design
A22: 18 | C22: Incident Report | E22: Positive | G22: Log in as Incident Management Team Member. | K22: In Design
A23: 19 | C23: Incident Report | E23: Positive | G23: Navigate to Incident Cases and open the same Incident Case record. | K23: In Design
A24: 20 | C24: Incident Report | E24: Positive | G24: Verify whether the Escalation Level field is visible on the page and whether it is populated. | I24: For Incident Management Team Member, the Escalation Level field is: Visible on the Incident Case record page (same relevant section as Admin), and Populated with the correct value (matches expected / matches Admin view). | K24: In Design
A25: 21 | C25: Incident Report | E25: Positive | K25: In Design
A26: 22 | B26: Verify Salesforce Case Record Validation | C26: Incident Report | E26: Positive | G26: Submit incident from portal. | K26: In Design
A27: 23 | C27: Incident Report | E27: Positive | G27: Login to Salesforce backend | K27: In Design
A28: 24 | C28: Incident Report | E28: Positive | G28: Search for newly created Case. | I28: Case record exists. Case fields populated correctly: Subject Category Concern Incident Date Case Origin = Experience Portal Contact & Account linked correctly. | K28: In Design
A29: 25 | B29: Verify Incident Ownership / PSG Assignment | C29: Incident Report | D29: Incident Ownership / PSG Assignment | E29: Positive | G29: Submit incident. Open case in Salesforce. | I29: Case assigned to correct: Queue OR Vendor Incident PSG Ownership matches design. No incorrect manual owner. | K29: In Design
A30: 26 | B30: Verify non Admin user should not be able to create an Incident | C30: Incident Report | D30: Negative Test – Non Vendor Admin User | E30: Positive | G30: Login as standard Experience user. Attempt direct URL access to Incident page. | I30: Access denied OR Redirected to homepage. No backend record created. | K30: In Design
A31: 27 | B31: Verify Create Incident via Email (Email-to-Case) Gets created successfully | C31: Incident Report | D31: Email-to-Case | E31: Positive | F31: Email-to-Case configured. ECMS intake address active. | G31: Send email to ECMS intake address. Include: Subject Description | I31: Case automatically created in Salesforce. Case Origin = Email Subject populated from email subject. Description populated from email body. Contact auto-associated (if match found). | K31: In Design
A32: 28 | B32: Verify ECMS Incident Intake Team should be able to create a case via salesforce, Create Incident via Salesforce UI | C32: Incident Report | D32: Create Incident via Salesforce UI | E32: Positive | G32: Login as Internal User. Navigate to Cases → New. | K32: In Design
A33: 29 | B33: Verify system should automatically assign case FCC for FCC Account | C33: Incident Report | D33: Auto-Routing to Intake Team | E33: Positive | G33: Select Record Type. Enter: Account Site Subject Category Click Save. | I33: Case successfully created. Record saved without errors. Routed automatically to Intake Team FCC | K33: In Design
A34: 30 | B34: Verify system should automatically assign case to Intake Team for CBO Account | C34: Incident Report | D34: Auto-Routing to Intake Team | E34: Positive | G34: Select Record Type. Enter: Account Site Subject Category Click Save. | I34: Case successfully created. Record saved without errors. Routed automatically to Intake Team TCO | K34: In Design
A35: 31 | B35: Verify Escalation Level Auto Calculation, Create case that qualifies for Escalation Level 1 | C35: Incident Report | D35: Escalation Level 1 Trigger | E35: Positive | I35: Escalation Level updated to Level 1. Notification triggered. Header view reflects escalation status. | K35: In Design
A36: 32 | B36: Verify when an Incident Management Team Update , confirm escalation level changes as per user action | C36: Incident Report | D36: Escalation Level change | E36: Positive | F36: Existing Escalation exist | G36: Building and Facility Safety and Security Facility and Maintenance Program is seeking to relocate to a new location CHANGE TO Building and Facility Safety and Security Facility and Maintenance Infant (under 12 months) room(s) does not have one crib or bassinet per child | I36: Confirm Escalation level change to 3 | K36: In Design
A37: 33 | B37: Vendor is not able to select site from checklist | G37: Login to Portal ->Click on Report Incident Fill the Required Fields → Select Account, Site | I37: Vendor Should be able to select site from the Checklist sites | J37: Vendor is not able to select site | K37: In Design | L37: https://prutech.atlassian.net/browse/DOEECMS-2066
A38: 34 | B38: Some fields are missing in Incident report case | G38: Login to Portal as CBO User Click on Report Incident → create new incidence report and save Issue 1 : Compare the Case in Portal and backend, In additional Information there are less feilds in backend compare to Portal some fields are missing Issue 2 : In backend We can see here Addtional Field is not there in Portal case form | I38: In both the Cases form should display the same feilds | J38: working as Fine | K38: In Design | L38: https://prutech.atlassian.net/browse/DOEECMS-2061
A39: 35 | B39: Account, site, subject are missing on Incident Cases | G39: Login to SF org as ECMS Intake Team Administrator Go to Incident Cases → Create New/Open which are already created. | I39: User should be able to see all the fields like Account, site, subject etc.. In Portal, User is able to see all the fields while creating but in salesforce org these fields were missing. | K39: In Design | L39: https://prutech.atlassian.net/browse/DOEECMS-2060
A40: 36 | B40: Account name is not a mandatory field but still getting error when trying to submit an Incident | G40: Log into Portal as FCCN User Click on Report Incident → Fill all the mandatory fields and Save. Note: Account and Site are not mandatory | I40: User should be able to submit Incident successfully but receiving error. | K40: In Design | L40: https://prutech.atlassian.net/browse/DOEECMS-2059
A52: 39
A53: 40

Sheet Checlklist-&Template
A1: =COUNT(A3:A70) -> 61 | B1: Total Test Cases
A2: Test Case ID | B2: Test Scenario | C2: Module / Feature | D2: Functionality | E2: TestType | F2: Preconditions | G2: Test Steps | H2: Test Data | I2: Expected Result | J2: Status | K2: Priority | L2: Defect Retest reference
A3: 1 | B3: Verify external userECMS_External_Checklist_Viewers PSG should only be allowed to populate checklist items and should not be allowed to change/update at the checklist template level | F3: External user exists with ECMS_External_Checklist_Viewers PSG; at least one checklist is assigned to the user. | G3: Login as external user → Navigate to Checklists | I3: Assigned checklist opens successfully | J3: Pass | L3: https://prutech.atlassian.net/browse/DOEECMS-1921
A4: 2 | G4: User click Edit and attempt to edit CHECKLIST Name, Owner, Envelope section, | I4: Confirm system should not allow user to edit | J4: Pass
A5: 3 | G5: Now user populate Checklist items | I5: Confirm system should allow user to populate | J5: Pass
A6: 4 | B6: Verify internal manager can create Checklisttemplates, author items, activate, assign, review, close/archive/reassign. | F6: Internal user exists with ECMS_Internal_Checklist_Manager PSG. | G6: Login as internal manager Launch ECMS App via app launcher AND Navigate to Checklist Templates Tab | I6: All admin actions available and executed successfully per role permissions. | J6: Pass
A7: 5 | G7: Click New button And enter Checklist Template Name and Click Save | I7: Confirm Checklist Template is created successfully | J7: Pass
A8: 6 | G8: Navigate to Checklist Template Items and click new | I8: Confirm New Checklist Template Item window should display Confirm Checkist template field is pre-populated Confirm Question section should have checklist template item label Required checkbox, Data Type, Due Date, section should have default due date and due date type field should exist. | J8: Pass
A9: 7 | G9: Populate the question section and add few questions required and add few questions optional Select Data type Text click Save Npte: Repeat this step multiple times depends Also add sequences | I9: Confirm all required and optional uestions are added successfully | J9: Pass
A10: 8 | G10: Navigate to Checklist Template that you just created and make it Active and click mark as current status | I10: Confirm checklist is now ACTIVE | J10: Pass
A11: 9 | G11: Click "Assign Checklist " | I11: Confirm Assign checklist page should display with the Checklist Name Envelope section having Respondent User field, Stage field, Notification frequency field and expiry date/time fields | J11: Pass
A12: 10 | G12: STEP10: select a respondent user who has ECMS_External_Checklist_Viewers PSG Populate notification frequency to Hour. select stage sent to respondent and populate expire date and click send checklists | J12: Pass
A13: 11 | G13: Now login as a the same external user ECMS_External_Checklist_Viewers PSG AND Navigate to Checklist tab | I13: Confirm the checklist that was just sent should exist | J13: Pass
A14: 12 | G14: Click on the Checklist and navigate to questionaire and click submit without populating the required fields | I14: Confirm system should display an error message | J14: Pass
A15: 13 | G15: Wait for an hour and then Navigate to Bell Icon | I15: Confirm Bell notification has notfication activated for the user | J15: Pass
A16: 14 | G16: User click Mark all as read | I16: Confirm all notification should now be removed | J16: Pass
A17: 15 | G17: Now populate all the required fields and optional fields and click Save | I17: confirm response is submitted successfully | J17: Pass
A18: 16 | G18: LogOut and login again | I18: Confirm user is successfully logged in again | J18: Pass
A19: 17 | G19: Navigate to the same checklist that was saved | I19: Confirm save questionaire should be saved and no changes occured | J19: Pass
A20: 18 | G20: Now CLICK sUBMIT | I20: Confirm system successfully processed the checklist | J20: Pass
A21: 19 | B21: Verify Checklist Manager should be able to view submitted Checklist by the External User | G21: Login as a Checklist Manager and navigate to ECMS via app launcher Then navigate to checklist | I21: Confirm user land on checklist | J21: Pass
A22: 20 | G22: Select submitted checklist by the external user in scenario 1 (Above) and Try to Edit User responses | I22: Confirm system should not allow user to edit submitted responses | J22: Fail
A23: 21 | B23: Verify non-manager internal user cannot create/activate templates or assign checklists. | F23: User without ECMS_Internal_Checklist_Manager PSG. | G23: Login as unauthorized user (Login as an Operations Director / operations Analyst. Navigate to Checklist Via app launcher | I23: Confirm Checklist should not exist | J23: Pass | L23: https://prutech.atlassian.net/browse/DOEECMS-1922
A24: 22 | B24: Verify system blocks template save when required fields are missing. | F24: Internal manager access. | G24: Login as a checklist manager AND Navigate to Checklist Via app launcher | I24: System display checklist Template page | J24: Pass
A25: 23 | G25: Leave Name/Respondent Type/Dates blank → Save. | I25: System shows validation messages; template not saved.
A26: 24 | B26: Verify Checklist Manager Should NOT be able to create a Checklist if expiration date is selected in the past | G26: Login as a Checklist Manager | I26: Logged in successfully | J26: Pass | L26: https://prutech.atlassian.net/browse/DOEECMS-1921
A27: 25 | G27: Launch ECMS via app launcher | J27: Pass
A28: 26 | G28: Navigate to Checklist Tab and click New | I28: Confirm Two radio button should display, From Template Create a New checklist without Template | J28: Pass | L28: https://prutech.atlassian.net/browse/DOEECMS-1922
A29: 27 | G29: Select Create a New checklist without Template radio button and click Next | I29: Confirm user view Information and envelope section | J29: Pass
A30: 28 | G30: DO not populate any fields and click save draft | I30: Confirm system respond with error messages for Checklist name field, respondent user field, expire date/time field | J30: Pass
A31: 29 | G31: Now populate checklist Name field and select respondent user, Select expire Date / Time in the past and click save | I31: Confirm system should respond with an error message not to allow user to create a checklist | J31: Fail
A32: 30 | B32: The system currently allows users to clone a checklist template that is expired and inactive. During the cloning process, the system copies the original Expiration Date and Time values into the new checklist record. As a result, the newly cloned checklist automatically becomes Inactive due to current logic | F32: Existing checklist template is expired and marked Inactive User has Checklist Manager permissions | G32: Login as Checklist Manager Navigate to the Checklist tab | I32: User lands on checklist | J32: Pass
A33: 31 | G33: Click New | I33: checklist page is displayed | J33: Pass
A34: 32 | G34: Select an existing checklist template that is expired and inactive | I34: user selection is selected | J34: Pass
A35: 33 | G35: Click the Clone button | I35: Checkistem Template is successfully cloned | J35: Pass
A36: 34 | G36: Observe the cloned checklist record | I36: The system should prevent cloned checklists from inheriting past expiration date/time values. When cloning: The Expiration Date and Time field should either be left blank, OR The system should prevent past dates from being saved, OR The system should not automatically mark cloned checklist records as inactive based on inherited past expiration values The cloned checklist should remain Active unless a valid future expiration date is explicitly set. | J36: Fail
A37: 35 | B37: Verify system enforces date logic: Expiration/Due date must be after Start date. | F37: Internal manager access. | G37: New Template → Set Start Date after Expiration date → Save. | I37: Validation error displayed; save blocked. | J37: Pass
A38: 36 | J38: Pass
A39: 37 | J39: Pass
A40: 38 | B40: Verify template items can be created with sequencing, label, type, and required flag. | F40: Template exists in Draft. | G40: Open Draft Template → Add Template Item → Enter Seq, Label, Type, Required → Save item. | I40: Item is saved and appears in template item list. | J40: Pass
A41: 39 | B41: Verify multiple items can be added and displayed in correct sequence order. | F41: Template exists in Draft. | G41: Navigate to existing checklist template and add more than 20 Checklist Template Items | I41: Confirm user should be able them successfully | J41: Pass
A42: 40 | B42: Verify Checklist Manager should be able to Add multiple Checklist Template Items | F42: Template exists in Draft. | G42: Navigate to existing Checklist Template and then navigate to checklist Template Item and click New | J42: Pass
A43: 41 | B43: Verify system blocks item save when required item fields are missing (e.g., Label/Type). | F43: Template exists in Draft. | G43: Add Template Item → Leave Label/Type blank → Save. | I43: Validation error displayed; item not saved. | J43: Pass
A44: 42 | B44: Verify Template cannot be activated when no Checklist Template item exist | F44: Template exists in Draft. | G44: Navigate to existing Checklist Template and then Change its status from draft to Active and click mark status as complete | I44: Confirm system should respond with an error message | J44: Pass
A45: 43 | B45: Verify updating an item persists changes and maintains version/audit trail (if enabled). | F45: Template and item exist; versioning/audit enabled. | G45: Edit existing item (Label/Required) → Save → Review audit/version history. | I45: Changes saved; version/audit entry recorded as expected. | J45: Pass
A46: 44 | B46: Verify activation blocked when no items exist (draft until item exists). | F46: Template exists with no items. | G46: Open template → Attempt Activate Template. | I46: Activation blocked; message indicates items required; template remains Draft. | J46: In Design
A47: 45 | B47: Verify template can be activated when at least one item exists. | F47: Template in Draft with ≥1 item. | G47: Open template → Review items list → Activate Template (Mark as Active). | I47: Template status becomes Active; available for assignment. | J47: Pass
A48: 46 | B48: Verify assignment can be created with respondent, expiry date, and reminder frequency. | F48: Active template exists; respondent user exists. | G48: Assign Checklist → Select Respondent → Set Expire Date → Set Frequency → Save assignment. | I48: Assignment created; schedule is set; respondent sees assigned checklist. | J48: Pass
A49: 47 | B49: Verify system blocks assignment if expire date is in the past or before assignment date. | F49: Active template exists. | G49: Assign Checklist → Set Expire Date in past → Save. | I49: Confirm Checklist Template should be auto inactivated | J49: Pass
A50: 48 | B50: Verify System should send email notification to external user when checklist item is sent | G50: Create checklist template with frequency with an hourly and sent to respondent by click sent checklist after selecting a respondent | I50: Confirm system should sent the checklist successfully | J50: Pass
A51: 49 | G51: login to external user email | I51: Confirm user should recieve checklist item survey notification in inbox | J51: Pass
A52: 50 | J52: Pass
A53: 51 | B53: Verify overdue/expired checklist supports extend/resend and reschedules reminders. | F53: Assigned checklist past expiry; expiry handling enabled. | G53: Allow checklist to become overdue → Trigger extend/resend → Verify reminders rescheduled. | I53: Checklist expiry handled; extend/resend works; schedule updated; reminders sent. | J53: Pass
A54: 52 | B54: Verify respondent can open assigned checklist and enter responses. | F54: Checklist assigned to respondent. | G54: Login as respondent → Open Assigned Checklist → Enter responses in fields. | I54: Responses captured; checklist ready for submission validation. | J54: Pass
A55: 53 | B55: Verify submission blocked if required item response is missing; user can fix and retry. | F55: Checklist assigned; at least one item Required. | G55: Open checklist → Leave required item blank → Submit. | I55: Validation error shown; checklist not submitted; user remains in fix-and-retry loop. | J55: Pass
A56: 54 | B56: Verify type/range/date validations block invalid responses and allow fix & retry. | F56: Checklist assigned; items with validation rules exist. | G56: Enter invalid value (wrong type/out of range) → Submit → Fix value → Resubmit. | I56: Error shown on invalid attempt; submission succeeds after correction. | J56: Pass
A57: 55 | B57: Verify valid checklist submission persists responses and audit log. | F57: Checklist assigned and responses valid. | G57: Enter valid responses → Submit checklist. | I57: Checklist submitted; responses persisted; audit record created. | J57: Pass
A58: 56 | B58: Verify manager can review submitted checklist and validate responses. | F58: Checklist submitted by respondent. | G58: Login as manager → Open submission → Review responses → Validate. | I58: Manager can view responses; review/validation recorded. | J58: Pass
A59: 57 | B59: Verify manager can close checklist after review completion. | F59: Checklist submitted and reviewed. | G59: Open submission → Close checklist. | I59: Status updates to Closed; respondent cannot edit. | J59: Pass
A60: 58 | B60: Verify archive removes checklist from active lists but retains history/audit. | F60: Checklist exists and eligible for archive. | G60: Archive checklist → Verify active vs archive views. | I60: Not shown in active; visible in archive/history; audit retained. | J60: Pass
A61: 59 | B61: Verify reassign updates respondent access and reschedules notifications. | F61: Assignment exists; new respondent available. | G61: Reassign checklist → Save → Verify access for old/new respondents → Verify notification schedule. | I61: Old respondent loses access; new respondent gains access; reminders rescheduled. | J61: Pass
A62: 60 | B62: Validate core data elements captured across the full lifecycle. | F62: At least one full lifecycle run completed (create template → assign → submit → review). | G62: Review backend records and related lists for key data elements. | I62: All required data elements present and consistent. | J62: Pass
A63: 61 | B63: Verify List view for Checking, As a Checklist Manager when I create a Checklist and assign to a respondent then I should see those checklist under "My Checklist" list view" | G63: Checklist Manager Created a Checklist AND Respondent responded to the checklist and submit via external portal | J63: Pass
G64: Checklist Manager login to salesforce and navigate to checklist and My checklist | I64: System should show checklist that checklist manager created | J64: Pass

Sheet QA Test Summary
A1: Green | B1: Internal reviewed
C2: Test Cases
B3: Module | C3: # Created | D3: # Design | E3: # Reviewed | F3: # Passed | G3: # Failed | H3: # Blocked | I3: # No Run | J3: Blocked% | K3: Failed% | L3: Passed% | M3: No Run %
B4: Budget | C4: =COUNT(Budget!$A$3:$A$1048576) -> 146 | D4: =COUNTIF(Budget!$J$3:$J$1048576,"In Design")+COUNTIF(Budget!$J$3:$J$1048576,"In design") -> 20 | E4: =COUNTIF(Budget!$J$3:$J$1048576,"Reviewed")+COUNTIF(Budget!$J$3:$J$1048576,"Reviewed Completed") -> 142 | F4: 100 | G4: =COUNTIF(Budget!$J$3:$J$1048576,"Fail")+COUNTIF(Budget!$J$3:$J$1048576,"Failed") -> 0 | H4: =COUNTIF(Budget!$J$3:$J$1048576,"Blocked") -> 0 | I4: =COUNTIF(Budget!$J$3:$J$1048576,"No Run")+COUNTIF(Budget!$J$3:$J$1048576,"No run") -> 0 | J4: =IF($C4=0,0,$H4/$C4) -> 0 | K4: =IF($C4=0,0,$G4/$C4) -> 0 | L4: =IF($C4=0,0,$F4/$C4) -> 0.68493151 | M4: =IF($C4=0,0,$I4/$C4) -> 0
B5: Seat & Capacity | C5: =COUNT('Seats & Capacity'!$A$3:$A$1048576) -> 31 | D5: =COUNTIF('Seats & Capacity'!$I$3:$I$1048576,"In Design")+COUNTIF('Seats & Capacity'!$I$3:$I$1048576,"In design") -> 0 | E5: =COUNTIF('Seats & Capacity'!$I$3:$I$1048576,"Reviewed")+COUNTIF('Seats & Capacity'!$I$3:$I$1048576,"Reviewed Completed") -> 0 | F5: =COUNTIF('Seats & Capacity'!$I$3:$I$1048576,"Pass")+COUNTIF('Seats & Capacity'!$I$3:$I$1048576,"Passed") -> 27 | G5: =COUNTIF('Seats & Capacity'!$I$3:$I$1048576,"Fail")+COUNTIF('Seats & Capacity'!$I$3:$I$1048576,"Failed") -> 4 | H5: =COUNTIF('Seats & Capacity'!$I$3:$I$1048576,"Blocked") -> 0 | I5: =COUNTIF('Seats & Capacity'!$I$3:$I$1048576,"No Run")+COUNTIF('Seats & Capacity'!$I$3:$I$1048576,"No run") -> 0 | J5: =IF($C5=0,0,$H5/$C5) -> 0 | K5: =IF($C5=0,0,$G5/$C5) -> 0.12903226 | L5: =IF($C5=0,0,$F5/$C5) -> 0.87096774 | M5: =IF($C5=0,0,$I5/$C5) -> 0
B6: Screening | C6: =COUNT(Screening!$A$4:$A$1048576) -> 29 | D6: =COUNTIF(Screening!$I$4:$I$1048576,"In Design")+COUNTIF(Screening!$I$4:$I$1048576,"In design") -> 0 | E6: =COUNTIF(Screening!$I$4:$I$1048576,"Reviewed")+COUNTIF(Screening!$I$4:$I$1048576,"Reviewed Completed") -> 0 | F6: =COUNTIF(Screening!$I$4:$I$1048576,"Pass")+COUNTIF(Screening!$I$4:$I$1048576,"Passed") -> 26 | G6: =COUNTIF(Screening!$I$4:$I$1048576,"Fail")+COUNTIF(Screening!$I$4:$I$1048576,"Failed") -> 1 | H6: =COUNTIF(Screening!$I$4:$I$1048576,"Blocked") -> 1 | I6: =COUNTIF(Screening!$I$4:$I$1048576,"No Run")+COUNTIF(Screening!$I$4:$I$1048576,"No run") -> 0 | J6: =IF($C6=0,0,$H6/$C6) -> 0.034482759 | K6: =IF($C6=0,0,$G6/$C6) -> 0.034482759 | L6: =IF($C6=0,0,$F6/$C6) -> 0.89655172 | M6: =IF($C6=0,0,$I6/$C6) -> 0
B7: Enrollment | C7: =COUNT(Enrollment!$A$3:$A$1048576) -> 47 | D7: =COUNTIF(Enrollment!$I$3:$I$1048576,"In Design")+COUNTIF(Enrollment!$I$3:$I$1048576,"In design") -> 0 | E7: =COUNTIF(Enrollment!$I$3:$I$1048576,"Reviewed")+COUNTIF(Enrollment!$I$3:$I$1048576,"Reviewed Completed") -> 0 | F7: =COUNTIF(Enrollment!$I$3:$I$1048576,"Pass")+COUNTIF(Enrollment!$I$3:$I$1048576,"Passed") -> 41 | G7: =COUNTIF(Enrollment!$I$3:$I$1048576,"Fail")+COUNTIF(Enrollment!$I$3:$I$1048576,"Failed") -> 6 | H7: =COUNTIF(Enrollment!$I$3:$I$1048576,"Blocked") -> 0 | I7: =COUNTIF(Enrollment!$I$3:$I$1048576,"No Run")+COUNTIF(Enrollment!$I$3:$I$1048576,"No run") -> 2 | J7: =IF($C7=0,0,$H7/$C7) -> 0 | K7: =IF($C7=0,0,$G7/$C7) -> 0.12765957 | L7: =IF($C7=0,0,$F7/$C7) -> 0.87234043 | M7: =IF($C7=0,0,$I7/$C7) -> 0.042553191
B8: Attendance | C8: =COUNT(Attendance!$A$3:$A$1048576) -> 95 | D8: =COUNTIF(Attendance!$K$3:$K$1048576,"In Design")+COUNTIF(Attendance!$K$3:$K$1048576,"In design") -> 38 | E8: =COUNTIF(Attendance!$K$3:$K$1048576,"Reviewed")+COUNTIF(Attendance!$K$3:$K$1048576,"Reviewed Completed") -> 0 | F8: 80 | G8: =COUNTIF(Attendance!$K$3:$K$1048576,"Fail")+COUNTIF(Attendance!$K$3:$K$1048576,"Failed") -> 4 | H8: =COUNTIF(Attendance!$K$3:$K$1048576,"Blocked") -> 0 | I8: =COUNTIF(Attendance!$K$3:$K$1048576,"No Run")+COUNTIF(Attendance!$K$3:$K$1048576,"No run") -> 0 | J8: =IF($C8=0,0,$H8/$C8) -> 0 | K8: =IF($C8=0,0,$G8/$C8) -> 0.042105263 | L8: =IF($C8=0,0,$F8/$C8) -> 0.84210526 | M8: =IF($C8=0,0,$I8/$C8) -> 0
B9: Incident | C9: 56 | D9: =COUNTIF(Incident!$K$4:$K$1048576,"In Design")+COUNTIF(Incident!$K$4:$K$1048576,"In design") -> 56 | E9: =COUNTIF(Incident!$K$4:$K$1048576,"Reviewed")+COUNTIF(Incident!$K$4:$K$1048576,"Reviewed Completed") -> 0 | F9: 50 | G9: 5 | H9: =COUNTIF(Incident!$K$4:$K$1048576,"Blocked") -> 0 | I9: =COUNTIF(Incident!$K$4:$K$1048576,"No Run")+COUNTIF(Incident!$K$4:$K$1048576,"No run") -> 0 | J9: =IF($C9=0,0,$H9/$C9) -> 0 | K9: =IF($C9=0,0,$G9/$C9) -> 0.089285714 | L9: =IF($C9=0,0,$F9/$C9) -> 0.89285714 | M9: =IF($C9=0,0,$I9/$C9) -> 0
B10: Monitoring/Coaching log | C10: =COUNT('Coaching log'!$A$4:$A$1048576) -> 59 | D10: =COUNTIF('Coaching log'!$I$4:$I$1048576,"In Design")+COUNTIF('Coaching log'!$I$4:$I$1048576,"In design") -> 0 | E10: =COUNTIF('Coaching log'!$I$4:$I$1048576,"Reviewed")+COUNTIF('Coaching log'!$I$4:$I$1048576,"Reviewed Completed") -> 0 | F10: 45 | G10: =COUNTIF('Coaching log'!$I$4:$I$1048576,"Fail")+COUNTIF('Coaching log'!$I$4:$I$1048576,"Failed") -> 2 | H10: =COUNTIF('Coaching log'!$I$4:$I$1048576,"Blocked") -> 0 | I10: =COUNTIF('Coaching log'!$I$4:$I$1048576,"No Run")+COUNTIF('Coaching log'!$I$4:$I$1048576,"No run") -> 0 | J10: =IF($C10=0,0,$H10/$C10) -> 0 | K10: =IF($C10=0,0,$G10/$C10) -> 0.033898305 | L10: =IF($C10=0,0,$F10/$C10) -> 0.76271186 | M10: =IF($C10=0,0,$I10/$C10) -> 0
B11: Reporting / Dashboard | C11: 0 | D11: 0 | E11: 0 | F11: 0 | G11: 0 | H11: 0 | I11: 0 | J11: 0 | K11: 0 | L11: 0 | M11: 0
B12: Invoice | C12: =COUNT(Invoice!$A$3:$A$1048576) -> 38 | D12: =COUNTIF(Invoice!$J$3:$J$1048576,"In Design")+COUNTIF(Invoice!$J$3:$J$1048576,"In design") -> 0 | E12: =COUNTIF(Invoice!$J$3:$J$1048576,"Reviewed")+COUNTIF(Invoice!$J$3:$J$1048576,"Reviewed Completed") -> 0 | F12: =COUNTIF(Invoice!$J$3:$J$1048576,"Pass")+COUNTIF(Invoice!$J$3:$J$1048576,"Passed") -> 12 | G12: =COUNTIF(Invoice!$J$3:$J$1048576,"Fail")+COUNTIF(Invoice!$J$3:$J$1048576,"Failed") -> 0 | H12: =COUNTIF(Invoice!$J$3:$J$1048576,"Blocked") -> 26 | I12: =COUNTIF(Invoice!$J$3:$J$1048576,"No Run")+COUNTIF(Invoice!$J$3:$J$1048576,"No run") -> 0 | J12: =IF($C12=0,0,$H12/$C12) -> 0.68421053 | K12: =IF($C12=0,0,$G12/$C12) -> 0 | L12: =IF($C12=0,0,$F12/$C12) -> 0.31578947 | M12: =IF($C12=0,0,$I12/$C12) -> 0
B13: Checklist & Checklist Template | C13: ='Checlklist-&Template'!A1 -> 61 | D13: 3 | E13: =COUNTIF(Invoice!$J$3:$J$1048576,"Reviewed")+COUNTIF(Invoice!$J$3:$J$1048576,"Reviewed Completed") -> 0 | F13: 55 | G13: 3 | H13: =COUNTIF(Invoice!$J$3:$J$1048576,"Blocked") -> 26 | I13: =COUNTIF(Invoice!$J$3:$J$1048576,"No Run")+COUNTIF(Invoice!$J$3:$J$1048576,"No run") -> 0 | J13: =IF($C13=0,0,$H13/$C13) -> 0.42622951 | K13: =IF($C13=0,0,$G13/$C13) -> 0.049180328 | L13: =IF($C13=0,0,$F13/$C13) -> 0.90163934 | M13: =IF($C13=0,0,$I13/$C13) -> 0
B14: Procurement | C14: 0 | D14: 0 | E14: 0 | F14: 0 | G14: 0 | H14: 0 | I14: 0 | J14: 0 | K14: 0 | L14: 0 | M14: 0
B15: Document Management | C15: 0 | D15: 0 | E15: 0 | F15: 0 | G15: 0 | H15: 0 | I15: 0 | J15: 0 | K15: 0 | L15: 0 | M15: 0
B16: Data Migration | C16: 0 | D16: 0 | E16: 0 | F16: 0 | G16: 0 | H16: 0 | I16: 0 | J16: 0 | K16: 0 | L16: 0 | M16: 0
B17: ESMS Integration with External Systems | C17: 0 | D17: 0 | E17: 0 | F17: 0 | G17: 0 | H17: 0 | I17: 0 | J17: 0 | K17: 0 | L17: 0 | M17: 0
C18: 0 | D18: 0 | E18: 0 | F18: 0 | G18: 0 | H18: 0 | I18: =C18-(F18-G18) -> 0 | J18: =(H18/C18) -> #DIV/0! | K18: =IF($C18=0,0,$G18/$C18) -> 0 | L18: =IF($C18=0,0,$F18/$C18) -> 0 | M18: =I18/(F18+G18) -> #DIV/0!
C19: 0 | D19: 0 | E19: 0 | F19: 0 | G19: 0 | H19: 0 | I19: =C19-(F19-G19) -> 0 | J19: =(H19/C19) -> #DIV/0! | K19: =IF($C19=0,0,$G19/$C19) -> 0 | L19: =IF($C19=0,0,$F19/$C19) -> 0 | M19: =I19/(F19+G19) -> #DIV/0!
B20: Net Total | C20: =SUM(C4:C18) -> 562 | D20: =SUM(D4:D18) -> 117 | E20: =SUM(E4:E18) -> 142 | F20: =SUM(F4:F18) -> 436 | G20: =SUM(G4:G18) -> 25 | H20: =SUM(H4:H18) -> 53 | I20: =C20-(F20-G20) -> 151 | J20: =IF($C20=0,0,$H20/$C20) -> 0.09430605 | K20: =IF($C20=0,0,$G20/$C20) -> 0.044483986 | L20: =IF($C20=0,0,$F20/$C20) -> 0.77580071 | M20: =IF($C20=0,0,$I20/$C20) -> 0.26868327

Sheet Seats & Capacity
A1: =COUNT(A3:A44) -> 31
A2: Test Case ID | B2: Test Description/Title | C2: Module / Feature | D2: Preconditions | E2: Test Steps | F2: Test Data/ User | G2: Expected Result | H2: Actual outcome | I2: Status | J2: Defect Retest reference
A3: 1 | B3: verify that vendor is able lo login SF | C3: Seats& Capacity | E3: Login -->SF | F3: System admin | G3: Login sucessfully | H3: Working as Expected | I3: Pass
A4: 2 | B4: Verify that vendo user have setup has done perfect | C4: Seats& Capacity | D4: Check whether your user has PSG- Internal Admin | E4: ECMS -->Homepage | F4: Bunny/ 3-K class p | G4: Able to view home page | H4: Working as Expected | I4: Pass
A5: 3 | E5: Homepage-->setup | F5: Bunny/ 3-K class p | G5: All the required presetup has done for the user | H5: Working as Expected | I5: Pass
A6: 4 | E6: setup-->user | F6: Bunny/ 3-K class p | H6: Working as Expected | I6: Pass
A7: 5 | E7: User-->PSG Assign | F7: Bunny/ 3-K class p | H7: Working as Expected | I7: Pass
A8: 6 | E8: Back to Homepage | F8: Bunny/ 3-K class p | G8: Vendor is able to view seats and capacity by site class | H8: Working as Expected | I8: Pass
A9: 7 | B9: Verify that vendor is able View Seat Capacities by Site​ | C9: Seats& Capacity | E9: Homepage-->Account--> desired account link | F9: Bunny/ 3-K class p | H9: Working as Expected | I9: Pass
A10: 8 | E10: Account-->Quick link | F10: Bunny/ 3-K class p | H10: Working as Expected | I10: Pass
A11: 9 | E11: Account-->Quick link--> desired site | F11: Bunny/ 3-K class p | H11: Working as Expected | I11: Pass
A12: 10 | E12: Site-->Quicl links | F12: Bunny/ 3-K class p | H12: Working as Expected | I12: Pass
A13: 11 | E13: site-->Class desired link | F13: Bunny/ 3-K class p | H13: Working as Expected | I13: Pass
A14: 12 | B14: "the vendor is able to observe that seats are getting auto filled" | C14: Seats& Capacity | E14: Portal-->create Enrollment | F14: Bunny/ 3-K class p | G14: The seats auto updated when submitting enrollment | H14: working as Expected | I14: Pass
A15: 13 | E15: Portal--> submit enrolment | F15: Bunny/ 3-K class p | I15: Pass
A16: 14 | E16: Back to SF--> desired classes | F16: Bunny/ 3-K class p | I16: Pass
A17: 15 | E17: class-->select class | F17: Bunny/ 3-K class p | I17: Pass
A18: 16 | E18: class-->view | F18: Bunny/ 3-K class p | I18: Pass
A19: 17 | E19: site-->view the capacity | F19: Bunny/ 3-K class p | G19: Able to view the seat and capacity occupied | H19: Working as Expected | I19: Pass | J19: https://prutech.atlassian.net/browse/DOEECMS-1892 https://prutech.atlassian.net/browse/DOEECMS-1968
A20: 18 | B20: View a Full Seat Capacity Class ​ | C20: Seats& Capacity | E20: Site-->view the capacity --> Full | F20: Bunny/ 3-K class p | H20: Working as Expected | I20: Pass
A21: 19 | B21: Verify that Vendor is able to edit capacity for active enrolled classes | C21: Seats& Capacity | E21: Site-->view the capacity --> Full-->Edit | F21: Bunny/ 3-K class p | G21: Verify that Vendor is able to edit capacity for active enrolled classes | H21: the vendor is not able to edit the capacity as tere are active enrollments in the class and populated an error | I21: Fail | J21: https://prutech.atlassian.net/browse/DOEECMS-1586 https://prutech.atlassian.net/browse/DOEECMS-1893
A22: 20 | B22: Verify that vendor is able to submit enrolment for capacity is full related site | C22: Seats& Capacity | D22: the class capacity must be full | E22: Login-->portal | F22: Bunny/ 3-K class p | G22: While create an sumit enrollment, the enrolmemt is not able to submit and the error has to populate | H22: Working as Expected | I22: Pass
A23: 21 | C23: Seats& Capacity | E23: Create enrolment--> submit | F23: Bunny/ 3-K class p | H23: Working as Expected | I23: Pass
A24: 22 | B24: Verify that vendor is able to see the other related sites classes capacity in the portal | C24: Seats& Capacity | D24: Validation- The vendor is only able to see their own sites related capacity in the portal | E24: Provision contact-->functions | F24: Bunny/ 3-K class p | G24: The vendor is not able to see the other site related classes or Capacity in the Portal | H24: woorking As expected | I24: Pass
A25: 23 | E25: Provision contact-->Site | F25: Bunny/ 3-K class p | I25: Pass
A26: 24 | E26: Login--> Portal | F26: Bunny/ 3-K class p | I26: Pass
A27: 25 | E27: Portal-->Site | F27: Bunny/ 3-K class p | I27: Pass
A28: 26 | E28: Portal-->classes | F28: Bunny/ 3-K class p | I28: Pass
A29: 27 | E29: Portal-->classes-->View Capacity | F29: Bunny/ 3-K class p | I29: Pass
A30: 28 | B30: Related List Quick Links" not loading for Internal Admin user | E30: Login-->Internal admin Navigate-->site Site-->Quicl Links | F30: Bunny/ 3-K class p | G30: The Related List Quick Links should load and display all applicable quick links for the record. | H30: The section does not load; quick links are missing or the component remains blank and shows in processing. | I30: Fail | J30: https://prutech.atlassian.net/browse/DOEECMS-1886
A31: 29 | B31: Internal Administrators do not have access to the Dashboards app | E31: Log in as an ECMS Internal Administrator. Navigate to the App Launcher. Search for “Dashboards”. Observe that the Dashboards app is missing / not visible. | G31: Internal Administrators should see and access the Dashboards app in the App Launcher. They should be able to open the Seat Capacity Planning Dashboard and related reports. Dashboard access should be included as part of the ECMS Admin Internal permission set. | H31: working As expected | I31: Pass | J31: https://prutech.atlassian.net/browse/DOEECMS-1891
A32: 30 | B32: A defect has been identified in the ECMS Seat Capacity module where a Class record is being created or saved without a valid Seat Capacity value (0 or null), while the Seats Occupied field displays a positive number. | E32: Navigate to Sites Master → Classes. Create or open an existing Class record. Leave Seat Capacity = 0 or blank. Ensure the system displays Seats Occupied > 0 (already existing enrollments or data mismatch). Save the record. Observe that the system allows saving the Class, despite invalid/contradictory values. | G32: Seat Capacity must be a required numeric field. The system must not allow creation or update of a Class record unless a valid Seat Capacity value is provided. Seat Capacity should never be allowed to remain 0, blank, or null if Seats Occupied is greater than 0. A validation error message should prevent saving until corrected. | H32: The system allows Class creation or update with Seat Capacity = 0 / null. | I32: Fail | J32: https://prutech.atlassian.net/browse/DOEECMS-1890
A33: 31 | B33: Seat Capacity Planning Dashboard - Capacity Vs Occupancy by Seat Type Column chart/ Report is not Visible | E33: Navigate to the ECMS home screen. Click on the nine dots on the top navigation bar and type “Dashboards.” Click on “Dashboards.” Click “All Dashboards” in the left most navigation pane. Click on the “Seat Capacity Planning Dashboard” link in the leftmost column. Capacity Vs Occupancy by Seat Type Column chart/ Report is not Visible | G33: Capacity Vs Occupancy by Seat Type Column chart with Report should be displayed correctly | H33: Capacity Vs Occupancy by Seat Type Column chart/ Report is not Visible | I33: Fail | J33: https://prutech.atlassian.net/browse/DOEECMS-2030

Sheet Enrollment
A1: =COUNT(A3:A63) -> 47 | B1: Total test cases
A2: Test Case ID | B2: Test Description/Title | C2: Module / Feature | D2: Preconditions | E2: Test Steps | F2: Test Data/ User | G2: Expected Result | H2: Actual outcome | I2: Status | J2: Defect Retest reference
A3: 1 | B3: Verify that admin user logged into ECMS-SF | C3: Enrollment | E3: Login SF-->Correct Credentials | F3: Admin user | G3: Loggedin in SF | H3: Working as Expected | I3: Pass
A4: 2 | B4: Verify that admin can able to search a vendor-based contact user in home page | C4: Enrollment | D4: Vendor contact exists in the system | E4: Home page -->Search Vendor User | F4: Admin User | G4: Admin user is able to search Vendor User | H4: Working as Expected | I4: Pass
A5: 3 | B5: Verify that admin can open the vendor user profile | C5: Enrollment | D5: That vendor user shoul be Active | E5: Home page -->Select Vendor User | F5: Admin user | G5: Admin user is able to select vendor based contact user | H5: Working as Expected | I5: Pass
A6: 4 | B6: Enable partner as user | C6: Enrollment | E6: Vendor contact-->enable partner as user | F6: Admin user | G6: Admin is able to Enable partner as user | H6: Working as Expected | I6: Pass
A7: 5 | B7: Verify that the Provision Contact button is visible for the vendor user profile | C7: Enrollment | E7: Vendor contact-->Provision Contact | F7: Ravi Krishna | G7: The should be able Provision contact | H7: Working as Expected | I7: Pass
A8: 6 | B8: Admin can successfully provision the vendor contact assign required permission sets to the vendor user | C8: Enrollment | D8: Permissions should be assigned Perfectly | E8: Vendor contact-->view Partner-->assign Permissions | F8: Ravi Krishna | G8: The user should be able to assign permissions to the User | H8: Working as Expected | I8: Pass
A9: 7 | B9: Verify that admin can log in to Experience as the vendor user | C9: Enrollment | E9: Vendor Contact-->login Experience as user | F9: Ravi Krishna | G9: The vendor is able to login Experience as user into the portal | H9: Working as Expected | I9: Pass
A10: 8 | B10: Student Enrollment on portal | C10: Enrollment | E10: Portal-->Create Enrollment Tab | F10: Ravi Krishna | G10: Vendor should be able to see Student Enrollment and Create Enrollments links on portal | H10: Working as Expected | I10: Pass
A11: 9 | B11: Create a new student Enrollment | C11: Enrollment | E11: Create new Enrollment on portal -> Student Basic details | F11: Ravi Krishna | G11: Vendor should be able to Enter Basic Student Details - First name, Last name, Birthdate, gender, etc | H11: Working as Expected | I11: Pass
A12: 10 | B12: Student Information | C12: Enrollment | E12: Create new Enrollment on portal -> Fill student information | F12: Ravi Krishna | G12: Prefil information from basic information and Vendor should be able to enter more Student Information like salutation, race, place of birth, borough, district, mailing address etc. | H12: Working as Expected | I12: Pass
A13: 11 | B13: Information Validations | C13: Enrollment | D13: Info should be in right validation | E13: Create new Enrollment on portal ->Student information form validations | F13: Ravi Krishna | G13: System should perform validations for all required information being filled by the vendor and display errors for missing fields data. | H13: Working as Expected | I13: Pass
A14: 12 | B14: Fill Parents Information | C14: Enrollment | E14: Create new Enrollment on portal -> Fill Parent Guardian information | F14: Ravi Krishna | G14: Vendor should be able to enter Parent information like - Name, mobile, relationship, address, spoken language, etc. | H14: Working as Expected | I14: Pass
A15: 13 | B15: Parents info Validation | C15: Enrollment | E15: Create new Enrollment on portal -> Parent Guardian information validation | F15: Ravi Krishna | G15: System should perform validations for all required information being filled by the vendor and display errors for missing fields data. | H15: Working as Expected | I15: Pass
A16: 14 | B16: Enrollment Information Requested | C16: Enrollment | E16: Create new Enrollment on portal -> Fill Enrollment Information | F16: Ravi Krishna | G16: Vendor should be able to fill enrollment information like Program type, seat type, site, class, etc. | H16: Working as Expected | I16: Pass
A17: 15 | B17: Enrollment info Related Class Creation | C17: Enrollment | D17: Class creation should be created Based on which we provided program type | E17: Create new Enrollment on portal ->Enrollment Information class creation | F17: Ravi Krishna | G17: Vendor should be able to create a new class from the field itself if not already present. | H17: Working as Expected | I17: Pass
A18: 16 | B18: Create new Enrolment for existing Student | C18: Enrollment | E18: Create new Enrollment on portal -> EXISTING student | F18: Ravi Krishna | G18: Vendor should be able to enter the Basic Student Details and system shall detect if the data entered is for an exisiting student and display the child name to select | H18: Working as Expected | I18: Pass
A19: 17 | B19: SAVE Enrollment | C19: Enrollment | E19: Create new Enrollment on portal -> Finish Enrollment | F19: Ravi Krishna | G19: Vendors should be able to save an enrollment in Draft status before submitting it for approval | H19: Working as Expected | I19: Pass
A20: 18 | B20: EDIT Enrollment | C20: Enrollment | E20: Saved Enrollment-->Edit | F20: Ravi Krishna | G20: Vendors should be able to edit a saved enrollment that is in New or Draft status | H20: Working as Expected | I20: Pass
A21: 19 | B21: Finish Enrollment | C21: Enrollment | E21: Create new Enrollment on portal -> Validate and finish enrollment | F21: Ravi Krishna | G21: Vendors shall be to SUBMIT the enrolment for a student successfully after system validates the information provided. | H21: Working as Expected | I21: Pass
A22: 20 | B22: View Submitted Enrollment | C22: Enrollment | E22: Create new Enrollment on portal -> View submitted enrollment record | F22: Ravi Krishna | G22: Vendor should be able to view the submitted enollment record on the portal under the "Submitted enrollments" listview. | H22: Working as Expected | I22: Pass
A23: 21 | E23: Create new Enrollment on portal -> View submitted enrollment record | F23: RC Staff | G23: Vendor should no longer be able to edit a submitted status enrollment record | H23: Working as Expected | I23: Pass
A24: 22 | B24: View Submitted Enrollment Status | C24: Enrollment | E24: Create new Enrollment on portal -> View enrollment status | F24: Ravi Krishna | G24: Vendors shall be to see the correct status of the enrollment on the pipeline. | H24: Working as Expected | I24: Pass
A25: 23 | B25: Upload Documents | C25: Enrollment | E25: Saved Enrollment--> Upload documents | F25: Ravi Krishna | G25: Vendor should be able upload documents( Date of Birth ) | H25: Working as Expected | I25: Pass
A26: 24 | B26: Submit Enrollment | C26: Enrollment | E26: Saved Enrollment--> Submit Enrolment | F26: Ravi Krishna | G26: Vendor should be able to submit enrollment | H26: Working as Expected | I26: Pass
A27: 25 | B27: View new enrollment in SF, Notify Internal user | C27: Enrollment | D27: Internal User should be able to receive Notification for approval | E27: Home page--> Items to approve | F27: Enrollment Specialist | G27: Enrollment Specialist shouldget notified via email for approval request and see the newly created enrollment record in the salesforce | H27: Working as Expected | I27: Pass
A28: 26 | B28: Enrollment approval history | C28: Enrollment | E28: SF Enrollment Record-->View approval history | F28: Enrollment Specialist | G28: Enrollment Specialist should be able to go to approval history for approve, reject or reassign the enrollment apporval | H28: Working as Expected | I28: Pass
A29: 27 | B29: Enrollment approvals from Approvals app | C29: Enrollment | E29: App launcher-->Approval requests | F29: Enrollment Specialist | G29: Enrollment Specialist should be able to see pending approvals for the enrollment from "Approvals" on homepage | H29: Working as Expected | I29: Pass
A30: 28 | B30: Enrollment approval flow | C30: Enrollment | E30: Approval requests--> items to apoprove | F30: Enrollment Specialist | G30: Enrollment Specialist should be able to approve a student enrollment and system shall refelect the status on the record | H30: Working as Expected | I30: Pass
A31: 29 | B31: Enrollment Information Requested | C31: Enrollment | E31: Approval requests--> items to apoprove-->Information request | F31: Enrollment Specialist | G31: Enrollment Specialist should be able to request for additional information to the submitter | H31: Working as Expected | I31: Pass
A32: 30 | B32: Add requested information on portal | C32: Enrollment | E32: Portal-->Info Requsted Enrollment-->Update information | F32: Ravi Krishna | G32: Vendor should able to add requested information on the enrollment and re-submit it for the approval | H32: Working as Expected | I32: Pass
A33: 31 | B33: Approve Enrollment | C33: Enrollment | E33: Approval requests--> items to apoprove-->Approve | F33: Enrollment Specialist | G33: Enrollment Specialist is able to approve | H33: Working as Expected | I33: Pass
A34: 32 | B34: Active Enrollment | C34: Enrollment | E34: SF Enrollment Record-->Mark as active | F34: Enrollment Specialist | G34: Enrollment Specialist should be able to make Manually mark status as active | H34: Working as Expected | I34: Pass
A35: 33 | E35: Create Budget --> view Existing Active budgets --> Try to edit the record | F35: RC Staff | G35: Vendor should no longer be able to edit an Active status enrollment record | H35: Working as Expected | I35: Pass
A36: 34 | B36: Upload docs for a submitted Enrollment | C36: Enrollment | D36: Enrollment status should be in Active status | E36: Login to ECMS portal as a Vendor Go to Student Enrollments tab Open Enrollment which is in Active status Click Upload Document → Try to Upload Documents | F36: Ravi Krishna | G36: Vendor should able to upload documents successfully | H36: Received Exception | I36: Pass | J36: DOEECMS-1884
A37: 35 | B37: Create Enrollment for Existing Student | C37: Enrollment | D37: Already Enrollment should be submitted and in Active status for an existing student | E37: Loginto ECMS Portal as Vendor Go to Student Enrollments tab → Create New Enrollment Enter details of Existing Student Select Existing Student → Save | F37: Ravi Krishna | G37: There should be a proper message saying Enrollment already exists for this student. | H37: Received Exception | I37: Pass | J37: DOEECMS-1870
A38: 36 | B38: Student Enrollment – Step 1 Data "Updates" should preserve on Step 2 | E38: Start creating a new enrollment. In Step 1 – Basic Student Details, enter: First Name Last Name Birth Date Gender Click Next and proceed to Step 2 – Student Information Form. Click Back to return to Step 1. Modify any of the details. Click Next to return to Step 2. | F38: Ravi Krishna | G38: Step 2 should display updated student information based on the latest values entered in Step 1. Data should be refreshed and synchronized across steps. | H38: Working as Expected | I38: Pass | J38: DOEECMS-1841
A39: 37 | B39: If any enrollment record is in New/Draft status, Vendor should be notified with an email | E39: Navigate to Vendor Login Click on Student Enrollment Button Check if there are any records with New/ Draft status If yes, Vendor should get email with those record details | G39: Vendor should get email with those record details | H39: Not yet Received | I39: No Run
A40: 38 | B40: Deactivate a record which is in Active status | E40: Navigate to Vendor Login Click on Student Enrollment Button Open any Active student record On top Right dropdown, select Request Deactivation Fill the data and submit the request | F40: Ravi Krishna | G40: Deactivation request should be submitted successfully | H40: Working as Expected | I40: Pass
A41: 39 | B41: View the record on which Deactivation action is performed | E41: Navigate to Vendor Login Click on Student Enrollment Button Open the Active student record for which deactivation request is initiated In view check the reason and vendor details which were provided during Deactivation request action | G41: The reason and vendor details which were provided during Deactivation request action should be properly displayed. | I41: Pass
A42: 40 | B42: When Enrollment Specialists request additional information on a submitted enrollment, the system does not update the enrollment record status to “Information Requested” | C42: Enrollment | E42: Log in to Salesforce as an Enrollment Specialist. Navigate to an enrollment record with Status = Submitted Enrollment. Click the action Request Additional Information Add comments and Submit the request. | G42: The enrollment record status should automatically update from Submitted Enrollment → Information Requested in both salesforce and at the portal The “Request additional Information” button shall not display anymore and the status on approval request page shall show “Information or More details Requested” (as coded in system) The vendor user should see the enrollment on the Vendor Portal indicating that more information has been requested The enrollment should be listed: Under the 'Information Requested' list view for the vendor on the portal | H42: The enrollment record status does not change and stays as Submitted Enrollment The button ‘Request Additional Information’ still keeps displaying on the Approval Request page. Vendor users see no update on the Vendor Portal The enrollment does not display in the vendor portal 'Information Requested' list view | I42: Pass | J42: https://prutech.atlassian.net/browse/DOEECMS-1772
A43: 41 | B43: Enrollment Screen – Admission Date Field Showing Blank | E43: Log into Vendor Portal Navigate to Student Enrollments Tab Select existing Student Enrollment record On top left, Admission Date field is blank | G43: Student Enrollment Screen – Admission Date Field data should be populated successfully | H43: Student Enrollment Screen – Admission Date Field Showing Blank | I43: Fail | J43: https://prutech.atlassian.net/browse/DOEECMS-2042
A44: 42 | B44: When Enrollment is updated Inactive to Active, update Discharge Date to Blank | E44: Login to ECMS Portal as Vendor Navigate to Active Enrollment → Request for Deactivation → Discharge Date will populate Login to SF Org as Enrollment Specialist → Update status from Active to Inactive For the same record try to update the status from Inactive to Active → Then Discharge Date should update as Blank. | G44: To avoid confusion, When Enrollment status is updated from Inactive to Active then Discharge Date should update as Blank. | H44: Enrollment status is Active still system displays Discharge Date. | I44: Fail | J44: https://prutech.atlassian.net/browse/DOEECMS-2041
A45: 43 | B45: First date of attendance before DOB is accepting | E45: Portal → Create enrollment Give First date of attendance as before student DOB and finish | G45: The system should not allow the first DOA before DOB it should restrict | H45: It was allowing the first date of attendance before DOB | I45: Fail | J45: https://prutech.atlassian.net/browse/DOEECMS-2035
A46: 44 | B46: Vendor User is Unable to Navigate Back to Previous Steps After DOB Validation Error | E46: Log into Vendor Portal Navigate to Student Enrollments Button --> Click on Create New Enrollment Button Provide all the details DOB less than Pre-K condition In parent details Step, don't provide mandate data and click on next Some validation message comes for mandate field so provide data and proceed In final step, system validates DOB and Program Type condition and throws an exception So As a Vendor I have to go back to first step and change DOB But system is restricting me with the parent mandate details field validation message even though data is present | G46: System Should allow me to do modifications by navigating to previous pages when data is present for mandate fields | H46: System is restricting me with the parent mandate details field validation message even though data is present | I46: Fail | J46: https://prutech.atlassian.net/browse/DOEECMS-2031
A47: 45 | B47: Vendor User is Unable to Navigate Back to Previous Steps After DOB Validation Error | E47: Log into Vendor Portal Navigate to Student Enrollments Button --> Click on Create New Enrollment Button Provide all the details DOB less than Pre-K condition In parent details Step, don't provide mandate data and click on next Some validation message comes for mandate field so provide data and proceed In final step, system validates DOB and Program Type condition and throws an exception So As a Vendor I have to go back to first step and change DOB But system is restricting me with the parent mandate details field validation message even though data is present | G47: System Should allow me to do modifications by navigating to previous pages when data is present for mandate fields | H47: System is restricting me with the parent mandate details field validation message even though data is present | I47: Fail | J47: https://prutech.atlassian.net/browse/DOEECMS-2031
A48: 46 | B48: Received error when trying to Mark status as Complete/Mark as Current Status | E48: Login as Enrollment Specialist to Salesforce Test Org Click on Items to Approve → Approve the Enrollment → Click on ‘Mark status as Complete’ | G48: Enrollment Specialist should be able to update the status as ‘Active’. | H48: Received below error | I48: Fail | J48: https://prutech.atlassian.net/browse/DOEECMS-2022
A49: 47 | B49: Student Birthdate and Program Type Eligibility Validation Missing | E49: Log into Vendor Portal Click on Create Enrollment button Provide all the data and Birthdate as yesterday and program type as Pre-K(4-5 years) Enrollment process is completed successfully without any errors | G49: There should be a validation based on Birthdate when irrelevant Program type is selected | H49: Enrollment process is completed successfully without any errors | I49: Pass | J49: https://prutech.atlassian.net/browse/DOEECMS-1989
G50: When Step1 is opened there should be a field with ‘Comments’ for the Vendor to see the Comments added by Enrollment Specialist. | H50: Working as Expected | I50: Pass | J50: https://prutech.atlassian.net/browse/DOEECMS-1954

Sheet Screening
A1: if Yellow | B1: Existing Defects
A2: =COUNT(A4:A49) -> 29
A3: Test Case ID | B3: Test Description/Title | C3: Module / Feature | D3: Preconditions | E3: Test Steps | F3: Test Data/ User | G3: Expected Result | H3: Actual outcome | I3: Status | J3: Existing Defect
A4: 1 | B4: Verify that admin user logged into ECMS-SF | C4: Student screening | E4: Login --> SF | F4: Bunny | G4: Admin user is logged into ECMS | H4: Working as expected | I4: Pass
A5: 2 | B5: Verify that admin can able to search a vendor-based contact user in home page | C5: Student screening | D5: Vendor contact exists in the system | E5: Homepage-->search--> vendor | F5: Bunny | G5: Vendor contact appears in search results | H5: Working as expected | I5: Pass
A6: 3 | B6: Verify that admin can open the vendor user profile | C6: Student screening | D6: that user should be active | E6: Homepage-->search--> vendor user Select | F6: Bunny | G6: Vendor user profile opens successfully and active | H6: Working as expected | I6: Pass
A7: 4 | B7: Enable partner as user and assign required permission sets to the vendor user | C7: Student screening | E7: Vendor user-->Assign Permissions | F7: Bunny | G7: The permissions are sucessfully assigned to the user | H7: Working as expected | I7: Pass
A8: 5 | B8: Verify that the Provision Contact button is visible for the vendor user profile | C8: Student screening | D8: Vendor contact is not yet provisioned | E8: Vendor user-->Provision Contact | F8: Bunny | G8: Provision Contact button is displayed on the profile | H8: Able to see Provision Contact | I8: Pass
A9: 6 | B9: Admin can successfully provision the vendor contact | C9: Student screening | E9: Vendor user-->Provision Contact | F9: Bunny | G9: Contact is provisioned successfully ,Confirmation message is displayed | H9: Provision Contact was Successful | I9: Pass
A10: 7 | B10: Verify that admin can log in to Experience as the vendor user | C10: Student screening | D10: Vendor user is active and site is configured correctly | E10: Vendor user-->Login to Portal | F10: Bunny | G10: Admin successfully logged in Portal as vendor user | H10: Working as Expected | I10: Pass
A11: 8 | B11: You can verify here the student screening tab is visible | C11: Student screening | D11: Screening tab visibility with the right permission set | E11: Portal-->home page --> Screening tab | F11: Bunny | G11: The right permissions are added so you can able to see | H11: Working as expected | I11: Pass
A12: 9 | B12: Verify the screening tab is not visible on portal | C12: Student screening | D12: Screening tab visibility without the right permission set | E12: Portal-->home page --> Screening tab | F12: Bunny | G12: should not display student screening tab | H12: Working as expected | I12: Pass
A13: 10 | B13: Verify that a Student Screening record is automatically created with “Not Started” status upon enrollment submission | C13: Student screening | D13: Enrollment is successfully submitted | E13: Screening tab-->Student Record | F13: Bunny | G13: Student Screening record is auto-created-Status is set to “Not Started” 45-day timeline tracking is initiated | H13: Working as expected | I13: Pass
A14: 11 | B14: The external vendor user can view “Not Started” Student Screenings using list view filter | C14: Student screening | E14: Screening tab-->Dropdown select filter not started | F14: Bunny | G14: “Not Started” list view displays all new screenings for assigned site(s) | H14: Working as expected | I14: Pass
A15: 12 | B15: Verify that external vendor user can open a Student Screening record for editing | C15: Student screening | D15: Screening record is in “Not Started” status | E15: Screening tab-->Dropdown select filter not started | F15: Bunny | G15: Student Screening record opens successfully in edit mode | H15: Working As expected | I15: Pass
A16: 13 | B16: Verify that screening questions dynamically change based on the response provided by the external user | C16: Student screening | D16: Screening record is editable | E16: Screening tab-->Fill form | F16: Bunny | G16: Subsequent questions change dynamically based on selected responses | H16: Working as expected | I16: Pass | J16: https://prutech.atlassian.net/browse/DOEECMS-1379
A17: 14 | B17: Verify that the system performs automated score calculations and validations while external user enters screening responses | C17: Student screening | D17: Sysytem shall allow the results calculate | E17: Screening tab-->Fill form | F17: Bunny | G17: Valid scores are calculated automaticallyand Invalid scores are rejected | H17: not working as expected , the systen does not calculating the results side by side and even the results are 0 then it has showing as above cutoff | I17: Fail | J17: https://prutech.atlassian.net/browse/DOEECMS-1861
A18: 15 | B18: The external vendor user can save the screening record as Draft or Submit and view calculated results | C18: Student screening | D18: Screening responses entered completely | E18: Screening tab-->Fill form-->Draft(or) Submit | F18: Bunny | G18: Draft saves record for future editing,Submit finalizes the screening,Results appear in the Results column of list view | H18: Working as expected | I18: Pass | J18: https://prutech.atlassian.net/browse/DOEECMS-1853
A19: 16 | B19: A Student Screening moves to Rescreen status when screening results are “Below Cutoff” | C19: Student screening | D19: External vendor user completed a screening | E19: Screening tab--> Student record--> Result | F19: Bunny | G19: Screening status automatically updates to “Rescreen” | H19: Working as expected | I19: Pass
A20: 17 | B20: The external vendor user can view Rescreening Students from the Student Screenings list view | C20: Student screening | D20: Screening records exist in Rescreen status | E20: Screening tab-->Dropdown select filter Rescreen | F20: Bunny | G20: Rescreening Students list view displays all students requiring rescreen | H20: Working as expected | I20: Pass
A21: 18 | B21: Verify that external vendor user can open a Rescreen screening record for editing | C21: Student screening | D21: Screening record is in Rescreen status | E21: Screening tab-->Dropdown--> filter Rescreen-> open | F21: Bunny | G21: Screening record opens successfully for rescreen editing | H21: Working as expected | I21: Pass
A22: 19 | B22: Verify that external vendor user can edit and update the screening record during rescreening | C22: Student screening | D22: Verify that admin Is able to edit values | E22: Screening tab-->Dropdown--> filter Rescreen-> edit | F22: Bunny | G22: Updated responses can be entered Changes are saved successfully | H22: Working as expected | I22: Pass
A23: 20 | B23: The external vendor user can view screenings not completed within 45 days using the list view | C23: Student screening | D23: Screenings exceed 45-day timeline | E23: Screening tab-->Dropdown select filter not Started in 45 Days | F23: Bunny | G23: “Not Completed in 45 Days” list view displays applicable records | I23: Pass
A24: 21 | B24: The vendor user receives an email notification when a screening is approaching due date | C24: Student screening | D24: Screening due date is approaching | F24: Bunny | G24: Email notification is sent to the vendor user for Rescreen | H24: Working as expected | I24: Pass
A25: 22 | B25: Vendor user receives an email notification for overdue screenings | C25: Student screening | D25: Screening not completed within 45 days | F25: Bunny | G25: Vendor user receives overdue notification email | I25: Pass
A26: 23 | B26: Verify that external vendor user can filter and view screenings by desired status | C26: Student screening | D26: Multiple screening statuses exist | E26: Screening tab--> Student record--> Result | F26: Bunny | G26: User can view screenings by selected status without errors | H26: Working as expected | I26: Pass
A27: 24 | B27: Verify Student Screening Status should Update After Vendor Submits Completed Screening Form | C27: Student screening/Update | E27: Log in as a Vendor User in the Vendor Portal. Navigate to a Student record where the Student Screening Status = Draft. Open the Student Screenings form. Enter all required screening information. Click Submit to complete the form. Return to the student’s Screening Status field on list view. Observe that the status remains “Draft” instead of updating. | G27: Once the vendor completes and submits the Student Screenings form, the Student Screening Status should automatically update to the appropriate next status (e.g., Submitted based on workflow rules). The new status should reflect that the screening is no longer in draft mode. | I27: Pass | J27: DOEECMS-1856
A28: 25 | B28: While giving the Results for screening the system was not get calculated side by side | E28: Log in as a Vendor User in the Vendor Portal. Navigate to the specific Student record. Open the Student Screenings form. Scroll through the form fields. Give results by random | F28: Bunny | G28: The System should get automatically calculate by side by while giving results | H28: The results were not getting calculate by the system. | I28: Pass | J28: https://prutech.atlassian.net/browse/DOEECMS-1861
A29: 26 | B29: On Portal - Remove "new" button for student screening | D29: Screening tab visibility | E29: Navigate to Student Screening. | F29: Anika Kumar | G29: No "New" button should be visible. | H29: No "New" button is visible. | I29: Blocked | J29: DOEECMS-1380
A30: 27 | B30: After selecting “YES” for Did you begin administering the home language survey (EMLLPP) for this child and thier family? | F30: Vinni | G30: The Questions Has to Populate | H30: the following questions do not populate to be answered. | I30: Pass | J30: https://prutech.atlassian.net/browse/DOEECMS-1379
A31: 28 | B31: DECE Policy button on Student Screening | C31: Student Screening | D31: Screening tab visibility | E31: Steps to Reproduce- Login to Portal as Vendor Admin Click on Student Enrollments → Open Active Enrollment → Click on Student Screening link Open Student screening record → Click on DECE Policy button | F31: Anika Kumar | G31: Policy page should be displayed | H31: Page no found error | I31: Pass | J31: DOEECMS-1912
A32: 29

Sheet E2E
B1: Module/ Feature | C1: BUDGET E2E FLOW - Vendor create budget - APPROVALS / rejection - REQUIRED FIELDS + Comments section - between external and internal - ) External user / internal user ) | D1: OA / OD APPROVED
B2: Account

Sheet Defect Dashboard
A1: share my sc

Sheet Invoice
A1: =COUNT(A3:A40) -> 38 | B1: Total Test Cases
A2: Test Case ID | B2: Test Scenario | C2: Module / Feature | D2: Functionality | E2: TestType | F2: Preconditions | G2: Test Steps | H2: Test Data | I2: Expected Result | J2: Status | K2: Priority | L2: Defect Retest reference
A3: 1 | B3: The Invoice Module requires the vendor user to have the “ECMS Invoices - External” permission set profile. | C3: Invoice | D3: Create | E3: Positive | F3: Vendor should assign with “ECMS Invoices - External” permission set | G3: Login to ECMS portal as a Vendor | I3: Vendor should have required Permisson set. | J3: Pass | L3: https://prutech.atlassian.net/browse/DOEECMS-1921
A4: 2 | E4: Positive | G4: Click on Invoice Tab --> New | J4: Pass
A5: 3 | B5: Vendor Admin (Experience User) Should NOT be able create a new Invoice for the Budget IF attendance for all enrollments under the Budget siteis not fullfiled | C5: Invoice | D5: Create | E5: Positive | F5: Budget Should be Approved by OA/OD Enrollment should be Active/Approved Previous month's attendance should be certified. Prior Month Invoice should be approved (if Exist) | G5: Login to ECMS portal as a Vendor | I5: Confirm New Invoice pop up should display | J5: Pass | L5: https://prutech.atlassian.net/browse/DOEECMS-1922
A6: 4 | E6: Positive | G6: Click on Invoice Tab --> New | J6: Pass
A7: 5 | C7: Invoice | E7: Negative | G7: User select Approved Budget from the list to invoice against and click Next button | I7: Confirm New Invoice pop up should display Hit Next to complete the PETS attestation and create the invoice for that month. | J7: Pass
A8: 6 | E8: Negative | G8: Click Next button | I8: Confirm system should display, Before submitting your invoice, please ensure you have certified your PETS Roster and Monthly Fire Drill Logs for completion. | J8: Pass
A9: 7 | C9: Invoice | E9: Negative | G9: Click Create Invoice button | I9: Confirm system should display, Please submit attendance for all enrollments under the Budget site and ensure they are certified before proceeding with invoice creation. | J9: Pass
A10: 8 | B10: Vendor Admin (Experience User) Should NOT be able create a new Invoice for the Budget If attendance is not certified. | E10: Negative | F10: Budget Should be Approved by OA/OD Enrollment should be Active/Approved Previous month's attendance should be certified. Prior Month Invoice should be approved (if Exist) | G10: Login to ECMS portal as a Vendor | I10: Confirm New Invoice pop up should display | J10: Pass
A11: 9 | C11: Invoice | E11: Negative | G11: Click on Invoice Tab --> New | J11: Pass
A12: 10 | E12: Negative | G12: User select Approved Budget from the list to invoice against and click Next button | I12: Confirm New Invoice pop up should display Hit Next to complete the PETS attestation and create the invoice for that month. | J12: Pass
A13: 11 | C13: Invoice | E13: Negative | G13: Click Next button | I13: Confirm system should display, Before submitting your invoice, please ensure you have certified your PETS Roster and Monthly Fire Drill Logs for completion. | J13: Pass
A14: 12 | E14: Negative | G14: Click Create Invoice button | I14: Confirm system should display, Please submit attendance for all enrollments under the Budget site and ensure they are certified before proceeding with invoice creation. | J14: Pass
A15: 13 | E15: Negative | G15: Click Site | I15: Confirm system should take user to classes page | J15: Blocked
A16: 14 | C16: Invoice | E16: Negative | G16: Do not select checkbox true "I Certify that the attendance Information reported on this Electronic Attendance form EAF is Correct. | I16: Confirm system should display "Please Select the checkbox to certify the attendance" | J16: Blocked
A17: 15 | E17: Negative | G17: select checkbox true "I Certify that the attendance Information reported on this Electronic Attendance form EAF is Correct. | I17: Confirm system should display, "Please Complete the Monthly Attendance before certifying" | J17: Blocked
A18: 16 | B18: Verify that OA receives notification and can review invoice for approval | C18: Invoice | D18: Approval/Notification | E18: Negative | F18: Invoice submitted; OA assigned/related notification configured | J18: Blocked
A19: 17 | B19: Verify Invoice is locked and cannot be edited after submission and confirm only user can view the invoice details. | D19: View/lock | E19: Negative | F19: Invoice submitted successfully | J19: Blocked
A20: 18 | B20: Verify vendor admin should not be able to proceed and create an invoice if monthly max on contract is exceeded | C20: Invoice | E20: Negative | F20: Invoice draft created; contract monthly max rule configured | J20: Blocked
A21: 19 | B21: Verify Vendor admin should not be allowed to create an invoice when certificates are expired | F21: Certificate validation fails (expired) | J21: Blocked
A22: 20 | B22: Verify vendor admin should not be allowed to save when DOC cost exceeds available funds | C22: Invoice | F22: Invoice draft created; available funds calculated | J22: Blocked
A23: 21 | B23: Verify vendor admin should not be allowed to create an invoice when budget is not approved | J23: Blocked
A24: 22 | B24: Verify vendor admin should be able to create an Invoice from main landing Page | F24: Budget Should be Approved by OA/OD Enrollment should be Active/Approved Previous month's attendance should be certified. Prior Month Invoice should be approved (if Exist) | G24: Click "Create Invoice" on main landing page , After login | J24: Blocked
A25: 23 | G25: Click New Button | I25: Confirm New Invoice pop up should display | J25: Blocked
A26: 24 | G26: Select Budget Name | I26: Confirm should display New Invioice page, and the Most recent Month you need an inviice for is July messge should be displayed due to start of fiscal year | J26: Blocked
A27: 25 | G27: Click Next button | I27: Confirm system display, "Before submitting your invoice, Please ensure your have certiified PETS Roster and monthly Fire Drill Logs for completion | J27: Blocked
A28: 26 | G28: Select Previous | I28: Confirm system take user back to previous page | J28: Blocked
A29: 27 | G29: Select Next Button | I29: Confirm system display, "Before submitting your invoice, Please ensure your have certiified PETS Roster and monthly Fire Drill Logs for completion | J29: Blocked
A30: 28 | G30: Select Create Invoice | I30: Please submit attendance for all enrollments under the Budget site and ensure they are certified before proceeding with invoice creation. | J30: Blocked
A31: 29 | B31: Verify supporting documents are required per line item during invoice creation | G31: Select Create Invoice. Line items require supporting docs. | J31: Blocked
A32: 30 | B32: Verify supporting documents are required per line item during invoice creation | G32: Try Save & Close without docs → attach docs → Save & Close. | I32: Blocked when missing; success after attaching required docs. | J32: Blocked
A33: 31 | B33: Verify OA can search an invoice and view invoice summary | G33: Login as an OA and navigate to Invoice | I33: Logged in successfully | J33: Blocked
A34: 32 | B34: Verify OA can search an invoice and view invoice summary | G34: Click an Invoice ID | I34: Invoice detail page is displayed | J34: Blocked
A35: 33 | B35: Verify OA can search an invoice and view invoice summary | G35: Click Invoice Summary | I35: Invoice accessible; correct status/summary displayed. | J35: Blocked
A36: 34 | B36: Verify only draft Invoice can be edited by OA after an invoice submission by an external user | G36: Login as an OA and navigate to Invoice | I36: Logged in successfully | J36: Blocked
A37: 35 | B37: Verify only draft Invoice can be edited by OA after an invoice submission by an external user | G37: Click an Invoice ID | I37: Invoice detail page is displayed | J37: Blocked
A38: 36 | B38: Verify only draft Invoice can be edited by OA after an invoice submission by an external user | G38: Edit an Invoice per within the rules | I38: Confirm user is able to edit and save | J38: Blocked
A39: 37 | B39: Verify OA add a commenys and they should appear in vendor approval history | G39: Click an Invoice ID | J39: Blocked
A40: 38 | B40: Verify OA add a commenys and they should appear in vendor approval history | G40: Add comments | I40: Confirm comments are added and audit trail is saved as per user entry for history purpose | J40: Blocked

Sheet Regression
C1: 46077 | D1: Defects Opened | E1: Defect ID | F1: Comments
B2: Module
B3: Budget
B4: Seat & Capacity
B5: Screening
B6: Enrollment
B7: Attendance
B8: Incident
B9: Monitoring/Coaching log
B10: Reporting
B11: Invoice

Sheet Defect RETEST

Sheet Team Tasks
B1: QA Team Assignments
B4: # | C4: Date | D4: Planned Due Date | E4: Tasks | F4: Priority | G4: Status | H4: % Completion | I4: Resource | K4: Status inputs | L4: Priority | M4: Weightage
B5: 1 | C5: 46052 | D5: 46082 | E5: Budget Module Test Cases Creation | F5: High | G5: In Progress | H5: 0.7 | I5: Anika Prasad | K5: Completed | L5: High | M5: 5
B6: 3 | C6: 46047 | D6: 46082 | E6: Attendance Module Test Cases | F6: High | G6: In Progress | H6: 0.7 | I6: Lakshmi Neeruthi | K6: In Progress | L6: Medium | M6: 3
B7: 4 | C7: 46048 | D7: 46082 | E7: Invoice Module Test Cases | F7: High | G7: In Progress | H7: 0.7 | I7: Fawad Rehman | K7: Not Started | L7: Low | M7: 1
B8: 5 | C8: 46047 | D8: 46082 | E8: Screening Modules Test Cases | F8: High | G8: In Progress | H8: 0.7 | I8: Niveditha Balguri
B9: 6 | C9: 46047 | D9: 46082 | E9: Enrollment | F9: High | G9: In Progress | H9: 0.7 | I9: Niveditha Balguri/Lakshmi Neeruthi | K9: Total Activities | L9: =COUNTIF($E$5:$E$28,"<>") -> 10
B10: 7 | C10: 46047 | D10: 46082 | E10: Seat & Capacity | F10: High | G10: In Progress | H10: 0.7 | I10: Niveditha Balguri/Lakshmi Neeruthi | K10: Completed Score | L10: =COUNTIFS($F$5:$F$28,$L$5,$G$5:$G$28,$K$5)*$M$5+COUNTIFS($F$5:$F$28,$L$6,$G$5:$G$28,$K$5)*$M$6+COUNTIFS($F$5:$F$28,$L$7,$G$5:$G$28,$K$5)*$M$7 -> 20
B11: 8 | C11: 46047 | D11: 46082 | E11: Monitoring/Coaching Logs Test Cases | F11: High | G11: Completed | H11: 1 | I11: Fawad Rehman | K11: Total Score | L11: =COUNTIF($F$5:$F$28,$L$5)*$M$5+COUNTIF($F$5:$F$28,$L$6)*$M$6+COUNTIF($F$5:$F$28,$L$7)*$M$7 -> 50
B12: 9 | C12: 46047 | D12: 46082 | E12: Incident Module Test Cases | F12: High | G12: Completed | H12: 1 | I12: Fawad Rehman | K12: % Completed | L12: =IFERROR(L10/L11,0) -> 0.4
B13: 10 | C13: 46068 | D13: 46082 | E13: Checklist | F13: High | G13: Completed | H13: 1 | I13: Fawad Rehman
B14: 11 | C14: 46068 | D14: 46082 | E14: Checklist Templates | F14: High | G14: Completed | H14: 1 | I14: Fawad Rehman | K14: Completed Score | L14: 1
K15: Total Score | L15: 10
K16: % Completed | L16: 0.1
K18: Completed Score | L18: 1
K19: Total Score | L19: 10
K20: % Completed | L20: 0.1
